<?xml version="1.0" encoding="ISO-8859-1" ?>
<!DOCTYPE tiles-definitions PUBLIC
       "-//Apache Software Foundation//DTD Tiles Configuration 2.0//EN"
       "http://tiles.apache.org/dtds/tiles-config_2_0.dtd">

<tiles-definitions>
	<!-- Default Main Template -->
	<definition name=".mainTemplate" template="/WEB-INF/jsp/common/main.jsp">
		<put-attribute name="title" value="BRP Beheerapplicatie" type="string" />
		<put-attribute name="header" value="/WEB-INF/jsp/common/header.jsp" />
		<put-attribute name="menu" value="/WEB-INF/jsp/common/menu.jsp" />
		<put-attribute name="berichten" value="/WEB-INF/jsp/common/messages.jsp" />
		<put-attribute name="body" value="blank" />
	</definition>
	
	<definition name=".bodyTemplate" template="/WEB-INF/jsp/common/body.jsp">
		<put-attribute name="tabmenu" value="/WEB-INF/jsp/common/blank.jsp" />
		<put-attribute name="tabcontent" value="/WEB-INF/jsp/common/blank.jsp" />
	</definition>
	
	<definition name="blank" template="/WEB-INF/jsp/common/blank.jsp"/>
	<definition name="error" template="/WEB-INF/jsp/error.jsp"/>
	<definition name="berichten" template="/WEB-INF/jsp/common/messages.jsp"/>	
</tiles-definitions>