<!-- Voorbeeldbericht BRPXML "SelectiesesultaatSet - Personen -->
<!-- ... -->
<!-- Casus: Standaard selectie uitgevoerd op 26 februari 2017 -->
<!-- ... -->
<brp:lvg_selVerwerkSelectieresultaatSet xmlns:brp="http://www.bzk.nl/brp/brp0200" xmlns:xsi="http://www.w3.org/2001/XMLSchema-instance"
	xsi:schemaLocation="http://www.bzk.nl/brp/brp0200 ../xsd/brp0200_lvgSelectie_Berichten.xsd">
	<brp:stuurgegevens>
		<brp:zendendePartij>199903</brp:zendendePartij>
		<brp:zendendeSysteem>BRP</brp:zendendeSysteem>
		<brp:ontvangendePartij>053001</brp:ontvangendePartij>
		<brp:referentienummer>7a7ca846-0cb9-4b87-bfa3-377fab6c7765</brp:referentienummer>
		<brp:tijdstipVerzending>2017-02-07T10:41:43.325Z</brp:tijdstipVerzending>
	</brp:stuurgegevens>
	<brp:selectiekenmerken>
		<brp:soortSelectieresultaatSet>Resultaatset personen</brp:soortSelectieresultaatSet>
		<brp:volgnummerSelectieresultaatSet>1</brp:volgnummerSelectieresultaatSet>
		<brp:soortSelectie>Standaard selectie</brp:soortSelectie>
		<brp:leveringsautorisatieIdentificatie>13</brp:leveringsautorisatieIdentificatie>
		<brp:dienstIdentificatie>49</brp:dienstIdentificatie>
		<brp:selectietaakIdentificatie>10123</brp:selectietaakIdentificatie>
		<brp:selectieDatum>2017-02-06</brp:selectieDatum>
		<brp:peilmomentMaterieelResultaat>2017-02-06</brp:peilmomentMaterieelResultaat>
		<brp:peilmomentFormeelResultaat>2017-02-06T09:22:32.329Z</brp:peilmomentFormeelResultaat>
		<brp:historievorm>Materieel</brp:historievorm>
	</brp:selectiekenmerken>
	<brp:geselecteerdePersonen>
		<brp:geselecteerdePersoon>
			<brp:meldingen>
				<brp:melding brp:objecttype="Melding" brp:referentieID="1">
					<brp:regelCode>R1343</brp:regelCode>
					<brp:soortNaam>Waarschuwing</brp:soortNaam>
					<brp:melding>Bij deze persoon is een verstrekkingsbeperking vastgelegd.</brp:melding>
				</brp:melding>
			</brp:meldingen>
			<brp:persoon brp:objectSleutel="prZCT6U+/G2CQFinwXiLmI8zCtIF+caDEhn5bSdroUM=" brp:objecttype="Persoon" brp:communicatieID="1">
				<brp:soortCode>I</brp:soortCode>
				<brp:afgeleidAdministratief brp:voorkomenSleutel="40">
					<brp:tijdstipRegistratie>2011-05-12T01:00:00.000Z</brp:tijdstipRegistratie>
					<brp:actieInhoud>448</brp:actieInhoud>
					<brp:tijdstipLaatsteWijziging>2017-02-08T11:31:58.152Z</brp:tijdstipLaatsteWijziging>
					<brp:tijdstipLaatsteWijzigingGBASystematiek>2017-02-08T11:31:58.152Z</brp:tijdstipLaatsteWijzigingGBASystematiek>
				</brp:afgeleidAdministratief>
				<brp:identificatienummers brp:voorkomenSleutel="97">
					<brp:tijdstipRegistratie>1995-10-01T01:00:00.000Z</brp:tijdstipRegistratie>
					<brp:actieInhoud>449</brp:actieInhoud>
					<brp:datumAanvangGeldigheid>1977-09-30</brp:datumAanvangGeldigheid>
					<brp:burgerservicenummer>116282526</brp:burgerservicenummer>
					<brp:administratienummer>1401019494</brp:administratienummer>
				</brp:identificatienummers>
				<brp:samengesteldeNaam brp:voorkomenSleutel="167">
					<brp:tijdstipRegistratie>1995-10-01T01:00:00.000Z</brp:tijdstipRegistratie>
					<brp:actieInhoud>449</brp:actieInhoud>
					<brp:datumAanvangGeldigheid>1977-09-30</brp:datumAanvangGeldigheid>
					<brp:indicatieNamenreeks>N</brp:indicatieNamenreeks>
					<brp:voornamen>Danielle</brp:voornamen>
					<brp:geslachtsnaamstam>Nolles</brp:geslachtsnaamstam>
				</brp:samengesteldeNaam>
				<brp:geboorte brp:voorkomenSleutel="159">
					<brp:tijdstipRegistratie>1995-10-01T01:00:00.000Z</brp:tijdstipRegistratie>
					<brp:actieInhoud>449</brp:actieInhoud>
					<brp:datum>1977-09-30</brp:datum>
					<brp:gemeenteCode>0207</brp:gemeenteCode>
					<brp:landGebiedCode>6030</brp:landGebiedCode>
				</brp:geboorte>
				<brp:geslachtsaanduiding brp:voorkomenSleutel="147">
					<brp:tijdstipRegistratie>1995-10-01T01:00:00.000Z</brp:tijdstipRegistratie>
					<brp:actieInhoud>449</brp:actieInhoud>
					<brp:datumAanvangGeldigheid>1977-09-30</brp:datumAanvangGeldigheid>
					<brp:code>V</brp:code>
				</brp:geslachtsaanduiding>
				<brp:inschrijving brp:voorkomenSleutel="40">
					<brp:tijdstipRegistratie>2011-05-12T01:00:00.000Z</brp:tijdstipRegistratie>
					<brp:actieInhoud>448</brp:actieInhoud>
					<brp:datum>1994-05-01</brp:datum>
				</brp:inschrijving>
				<brp:bijhouding brp:voorkomenSleutel="128">
					<brp:tijdstipRegistratie>2005-01-01T01:00:00.000Z</brp:tijdstipRegistratie>
					<brp:actieInhoud>450</brp:actieInhoud>
					<brp:datumAanvangGeldigheid>2005-01-01</brp:datumAanvangGeldigheid>
					<brp:partijCode>038501</brp:partijCode>
					<brp:bijhoudingsaardCode>I</brp:bijhoudingsaardCode>
					<brp:nadereBijhoudingsaardCode>A</brp:nadereBijhoudingsaardCode>
				</brp:bijhouding>
				<brp:bijhouding brp:voorkomenSleutel="127">
					<brp:tijdstipRegistratie>1994-05-01T01:00:00.000Z</brp:tijdstipRegistratie>
					<brp:actieInhoud>451</brp:actieInhoud>
					<brp:datumAanvangGeldigheid>1993-10-12</brp:datumAanvangGeldigheid>
					<brp:datumEindeGeldigheid>2005-01-01</brp:datumEindeGeldigheid>
					<brp:actieAanpassingGeldigheid>450</brp:actieAanpassingGeldigheid>
					<brp:partijCode>020701</brp:partijCode>
					<brp:bijhoudingsaardCode>I</brp:bijhoudingsaardCode>
					<brp:nadereBijhoudingsaardCode>?</brp:nadereBijhoudingsaardCode>
				</brp:bijhouding>
				<brp:voornamen>
					<brp:voornaam brp:voorkomenSleutel="66" brp:objectSleutel="52" brp:objecttype="PersoonVoornaam">
						<brp:tijdstipRegistratie>1995-10-01T01:00:00.000Z</brp:tijdstipRegistratie>
						<brp:actieInhoud>449</brp:actieInhoud>
						<brp:datumAanvangGeldigheid>1977-09-30</brp:datumAanvangGeldigheid>
						<brp:volgnummer>1</brp:volgnummer>
						<brp:naam>Danielle</brp:naam>
					</brp:voornaam>
				</brp:voornamen>
				<brp:geslachtsnaamcomponenten>
					<brp:geslachtsnaamcomponent brp:voorkomenSleutel="50" brp:objectSleutel="40" brp:objecttype="PersoonGeslachtsnaamcomponent">
						<brp:tijdstipRegistratie>1995-10-01T01:00:00.000Z</brp:tijdstipRegistratie>
						<brp:actieInhoud>449</brp:actieInhoud>
						<brp:datumAanvangGeldigheid>1977-09-30</brp:datumAanvangGeldigheid>
						<brp:volgnummer>1</brp:volgnummer>
						<brp:stam>Nolles</brp:stam>
					</brp:geslachtsnaamcomponent>
				</brp:geslachtsnaamcomponenten>
				<brp:naamgebruik brp:voorkomenSleutel="50">
					<brp:tijdstipRegistratie>1995-10-01T01:00:00.000Z</brp:tijdstipRegistratie>
					<brp:actieInhoud>449</brp:actieInhoud>
					<brp:code>E</brp:code>
					<brp:voornamen>Danielle</brp:voornamen>
					<brp:geslachtsnaamstam>Nolles</brp:geslachtsnaamstam>
				</brp:naamgebruik>
				<brp:adressen>
					<brp:adres brp:voorkomenSleutel="121" brp:objectSleutel="40" brp:objecttype="PersoonAdres">
						<brp:tijdstipRegistratie>2005-01-01T01:00:00.000Z</brp:tijdstipRegistratie>
						<brp:actieInhoud>450</brp:actieInhoud>
						<brp:datumAanvangGeldigheid>2005-01-01</brp:datumAanvangGeldigheid>
						<brp:soortCode>W</brp:soortCode>
						<brp:redenWijzigingCode>I</brp:redenWijzigingCode>
						<brp:datumAanvangAdreshouding>2005-01-01</brp:datumAanvangAdreshouding>
						<brp:gemeenteCode>0385</brp:gemeenteCode>
						<brp:afgekorteNaamOpenbareRuimte>Dreef</brp:afgekorteNaamOpenbareRuimte>
						<brp:huisnummer>12</brp:huisnummer>
						<brp:postcode>6942LJ</brp:postcode>
						<brp:landGebiedCode>6030</brp:landGebiedCode>
					</brp:adres>
					<brp:adres brp:voorkomenSleutel="120" brp:objectSleutel="40" brp:objecttype="PersoonAdres">
						<brp:tijdstipRegistratie>1994-05-01T01:00:00.000Z</brp:tijdstipRegistratie>
						<brp:actieInhoud>451</brp:actieInhoud>
						<brp:datumAanvangGeldigheid>1993-10-12</brp:datumAanvangGeldigheid>
						<brp:datumEindeGeldigheid>2005-01-01</brp:datumEindeGeldigheid>
						<brp:actieAanpassingGeldigheid>450</brp:actieAanpassingGeldigheid>
						<brp:soortCode>W</brp:soortCode>
						<brp:redenWijzigingCode>P</brp:redenWijzigingCode>
						<brp:aangeverAdreshoudingCode>I</brp:aangeverAdreshoudingCode>
						<brp:datumAanvangAdreshouding>1993-10-12</brp:datumAanvangAdreshouding>
						<brp:gemeenteCode>0207</brp:gemeenteCode>
						<brp:afgekorteNaamOpenbareRuimte>Dreef</brp:afgekorteNaamOpenbareRuimte>
						<brp:huisnummer>12</brp:huisnummer>
						<brp:postcode>6942LJ</brp:postcode>
						<brp:landGebiedCode>6030</brp:landGebiedCode>
					</brp:adres>
				</brp:adressen>
				<brp:nationaliteiten>
					<brp:nationaliteit brp:voorkomenSleutel="43" brp:objectSleutel="43" brp:objecttype="PersoonNationaliteit">
						<brp:tijdstipRegistratie>1994-05-01T01:00:00.000Z</brp:tijdstipRegistratie>
						<brp:actieInhoud>452</brp:actieInhoud>
						<brp:datumAanvangGeldigheid>1977-09-30</brp:datumAanvangGeldigheid>
						<brp:nationaliteitCode>0001</brp:nationaliteitCode>
						<brp:redenVerkrijgingCode>001</brp:redenVerkrijgingCode>
					</brp:nationaliteit>
				</brp:nationaliteiten>
				<brp:indicaties>
					<brp:onderCuratele brp:voorkomenSleutel="8" brp:objectSleutel="8" brp:objecttype="PersoonIndicatie">
						<brp:tijdstipRegistratie>2009-08-03T01:00:00.000Z</brp:tijdstipRegistratie>
						<brp:actieInhoud>454</brp:actieInhoud>
						<brp:datumAanvangGeldigheid>2009-08-03</brp:datumAanvangGeldigheid>
						<brp:waarde>J</brp:waarde>
					</brp:onderCuratele>
					<brp:signaleringMetBetrekkingTotVerstrekkenReisdocument brp:voorkomenSleutel="7" brp:objectSleutel="7" brp:objecttype="PersoonIndicatie">
						<brp:tijdstipRegistratie>2009-08-03T01:00:00.000Z</brp:tijdstipRegistratie>
						<brp:actieInhoud>453</brp:actieInhoud>
						<brp:waarde>J</brp:waarde>
					</brp:signaleringMetBetrekkingTotVerstrekkenReisdocument>
				</brp:indicaties>
				<brp:betrokkenheden>
					<brp:kind brp:objectSleutel="202" brp:objecttype="Betrokkenheid" brp:voorkomenSleutel="203">
						<brp:tijdstipRegistratie>1994-05-01T01:00:00.000Z</brp:tijdstipRegistratie>
						<brp:actieInhoud>457</brp:actieInhoud>
						<brp:familierechtelijkeBetrekking brp:objectSleutel="83" brp:objecttype="Relatie">
							<brp:relatie brp:voorkomenSleutel="90">
								<brp:tijdstipRegistratie>1994-05-01T01:00:00.000Z</brp:tijdstipRegistratie>
								<brp:actieInhoud>457</brp:actieInhoud>
							</brp:relatie>
							<brp:betrokkenheden>
								<brp:ouder brp:objectSleutel="203" brp:objecttype="Betrokkenheid" brp:voorkomenSleutel="202">
									<brp:tijdstipRegistratie>1994-05-01T01:00:00.000Z</brp:tijdstipRegistratie>
									<brp:actieInhoud>457</brp:actieInhoud>
									<brp:persoon brp:objectSleutel="prZCT6U+/G0//gS21Ykr/Y8zCtIF+caDEhn5bSdroUM=" brp:objecttype="Persoon">
										<brp:soortCode>P</brp:soortCode>
										<brp:identificatienummers brp:voorkomenSleutel="95">
											<brp:tijdstipRegistratie>1994-05-01T01:00:00.000Z</brp:tijdstipRegistratie>
											<brp:actieInhoud>457</brp:actieInhoud>
											<brp:datumAanvangGeldigheid>1977-09-30</brp:datumAanvangGeldigheid>
											<brp:administratienummer>1401019836</brp:administratienummer>
										</brp:identificatienummers>
										<brp:samengesteldeNaam brp:voorkomenSleutel="165">
											<brp:tijdstipRegistratie>1994-05-01T01:00:00.000Z</brp:tijdstipRegistratie>
											<brp:actieInhoud>457</brp:actieInhoud>
											<brp:datumAanvangGeldigheid>1977-09-30</brp:datumAanvangGeldigheid>
											<brp:indicatieNamenreeks>N</brp:indicatieNamenreeks>
											<brp:voornamen>Daniëlla</brp:voornamen>
											<brp:geslachtsnaamstam>Nolles</brp:geslachtsnaamstam>
										</brp:samengesteldeNaam>
										<brp:geboorte brp:voorkomenSleutel="157">
											<brp:tijdstipRegistratie>1994-05-01T01:00:00.000Z</brp:tijdstipRegistratie>
											<brp:actieInhoud>457</brp:actieInhoud>
											<brp:datum>1957-09-30</brp:datum>
											<brp:gemeenteCode>0207</brp:gemeenteCode>
											<brp:landGebiedCode>6030</brp:landGebiedCode>
										</brp:geboorte>
										<brp:geslachtsaanduiding brp:voorkomenSleutel="146">
											<brp:tijdstipRegistratie>1994-05-01T01:00:00.000Z</brp:tijdstipRegistratie>
											<brp:actieInhoud>457</brp:actieInhoud>
											<brp:datumAanvangGeldigheid>1977-09-30</brp:datumAanvangGeldigheid>
											<brp:code>V</brp:code>
										</brp:geslachtsaanduiding>
									</brp:persoon>
									<brp:ouderschap brp:voorkomenSleutel="96">
										<brp:tijdstipRegistratie>1994-05-01T01:00:00.000Z</brp:tijdstipRegistratie>
										<brp:actieInhoud>457</brp:actieInhoud>
										<brp:datumAanvangGeldigheid>1977-09-30</brp:datumAanvangGeldigheid>
									</brp:ouderschap>
								</brp:ouder>
							</brp:betrokkenheden>
						</brp:familierechtelijkeBetrekking>
					</brp:kind>
					<brp:ouder brp:objectSleutel="204" brp:objecttype="Betrokkenheid" brp:voorkomenSleutel="205">
						<brp:tijdstipRegistratie>1999-07-27T01:00:00.000Z</brp:tijdstipRegistratie>
						<brp:actieInhoud>458</brp:actieInhoud>
						<brp:familierechtelijkeBetrekking brp:objectSleutel="84" brp:objecttype="Relatie">
							<brp:relatie brp:voorkomenSleutel="91">
								<brp:tijdstipRegistratie>1999-07-27T01:00:00.000Z</brp:tijdstipRegistratie>
								<brp:actieInhoud>458</brp:actieInhoud>
							</brp:relatie>
							<brp:betrokkenheden>
								<brp:kind brp:objectSleutel="205" brp:objecttype="Betrokkenheid" brp:voorkomenSleutel="204">
									<brp:tijdstipRegistratie>1999-07-27T01:00:00.000Z</brp:tijdstipRegistratie>
									<brp:actieInhoud>458</brp:actieInhoud>
									<brp:persoon brp:objectSleutel="prZCT6U+/G1ogzlwP4W6iI8zCtIF+caDEhn5bSdroUM=" brp:objecttype="Persoon">
										<brp:soortCode>P</brp:soortCode>
										<brp:identificatienummers brp:voorkomenSleutel="96">
											<brp:tijdstipRegistratie>1999-07-30T01:00:00.000Z</brp:tijdstipRegistratie>
											<brp:actieInhoud>459</brp:actieInhoud>
											<brp:datumAanvangGeldigheid>1999-07-29</brp:datumAanvangGeldigheid>
											<brp:burgerservicenummer>106903421</brp:burgerservicenummer>
											<brp:administratienummer>1401020284</brp:administratienummer>
										</brp:identificatienummers>
										<brp:samengesteldeNaam brp:voorkomenSleutel="166">
											<brp:tijdstipRegistratie>1999-07-30T01:00:00.000Z</brp:tijdstipRegistratie>
											<brp:actieInhoud>459</brp:actieInhoud>
											<brp:datumAanvangGeldigheid>1999-07-29</brp:datumAanvangGeldigheid>
											<brp:indicatieNamenreeks>N</brp:indicatieNamenreeks>
											<brp:voornamen>Chantal</brp:voornamen>
											<brp:geslachtsnaamstam>Smit</brp:geslachtsnaamstam>
										</brp:samengesteldeNaam>
										<brp:geboorte brp:voorkomenSleutel="158">
											<brp:tijdstipRegistratie>1999-07-30T01:00:00.000Z</brp:tijdstipRegistratie>
											<brp:actieInhoud>459</brp:actieInhoud>
											<brp:datum>1999-07-27</brp:datum>
											<brp:gemeenteCode>0218</brp:gemeenteCode>
											<brp:landGebiedCode>6030</brp:landGebiedCode>
										</brp:geboorte>
									</brp:persoon>
								</brp:kind>
							</brp:betrokkenheden>
						</brp:familierechtelijkeBetrekking>
						<brp:ouderschap brp:voorkomenSleutel="97">
							<brp:tijdstipRegistratie>1999-07-27T01:00:00.000Z</brp:tijdstipRegistratie>
							<brp:actieInhoud>458</brp:actieInhoud>
						</brp:ouderschap>
					</brp:ouder>
					<brp:partner brp:objectSleutel="200" brp:objecttype="Betrokkenheid" brp:voorkomenSleutel="201">
						<brp:tijdstipRegistratie>1998-10-12T01:00:00.000Z</brp:tijdstipRegistratie>
						<brp:actieInhoud>456</brp:actieInhoud>
						<brp:huwelijk brp:objectSleutel="82" brp:objecttype="Relatie">
							<brp:relatie brp:voorkomenSleutel="89">
								<brp:tijdstipRegistratie>2010-02-01T01:00:00.000Z</brp:tijdstipRegistratie>
								<brp:actieInhoud>447</brp:actieInhoud>
								<brp:datumAanvang>1998-10-12</brp:datumAanvang>
								<brp:gemeenteAanvangCode>0218</brp:gemeenteAanvangCode>
								<brp:landGebiedAanvangCode>6030</brp:landGebiedAanvangCode>
								<brp:redenEindeCode>S</brp:redenEindeCode>
								<brp:datumEinde>2010-02-01</brp:datumEinde>
								<brp:gemeenteEindeCode>0385</brp:gemeenteEindeCode>
								<brp:landGebiedEindeCode>6030</brp:landGebiedEindeCode>
							</brp:relatie>
							<brp:relatie brp:voorkomenSleutel="88">
								<brp:tijdstipRegistratie>1998-10-12T01:00:00.000Z</brp:tijdstipRegistratie>
								<brp:actieInhoud>456</brp:actieInhoud>
								<brp:tijdstipVerval>1998-10-12T01:00:00.000Z</brp:tijdstipVerval>
								<brp:actieVerval>456</brp:actieVerval>
								<brp:datumAanvang>1998-10-12</brp:datumAanvang>
								<brp:gemeenteAanvangCode>0218</brp:gemeenteAanvangCode>
								<brp:landGebiedAanvangCode>6030</brp:landGebiedAanvangCode>
							</brp:relatie>
							<brp:betrokkenheden>
								<brp:partner brp:objectSleutel="201" brp:objecttype="Betrokkenheid" brp:voorkomenSleutel="200">
									<brp:tijdstipRegistratie>1998-10-12T01:00:00.000Z</brp:tijdstipRegistratie>
									<brp:actieInhoud>456</brp:actieInhoud>
									<brp:persoon brp:objectSleutel="prZCT6U+/G2Jwd38aGSKmB3NGDYqemGOEhn5bSdroUM=" brp:objecttype="Persoon">
										<brp:soortCode>P</brp:soortCode>
										<brp:identificatienummers brp:voorkomenSleutel="94">
											<brp:tijdstipRegistratie>2010-02-01T01:00:00.000Z</brp:tijdstipRegistratie>
											<brp:actieInhoud>447</brp:actieInhoud>
											<brp:datumAanvangGeldigheid>2010-02-01</brp:datumAanvangGeldigheid>
											<brp:burgerservicenummer>111785546</brp:burgerservicenummer>
											<brp:administratienummer>1401020149</brp:administratienummer>
										</brp:identificatienummers>
										<brp:samengesteldeNaam brp:voorkomenSleutel="164">
											<brp:tijdstipRegistratie>2010-02-01T01:00:00.000Z</brp:tijdstipRegistratie>
											<brp:actieInhoud>447</brp:actieInhoud>
											<brp:datumAanvangGeldigheid>2010-02-01</brp:datumAanvangGeldigheid>
											<brp:indicatieNamenreeks>N</brp:indicatieNamenreeks>
											<brp:voornamen>Koos</brp:voornamen>
											<brp:geslachtsnaamstam>Smit</brp:geslachtsnaamstam>
										</brp:samengesteldeNaam>
										<brp:geboorte brp:voorkomenSleutel="156">
											<brp:tijdstipRegistratie>2010-02-01T01:00:00.000Z</brp:tijdstipRegistratie>
											<brp:actieInhoud>447</brp:actieInhoud>
											<brp:datum>1975-11-18</brp:datum>
											<brp:gemeenteCode>0218</brp:gemeenteCode>
											<brp:landGebiedCode>6030</brp:landGebiedCode>
										</brp:geboorte>
										<brp:geslachtsaanduiding brp:voorkomenSleutel="145">
											<brp:tijdstipRegistratie>2010-02-01T01:00:00.000Z</brp:tijdstipRegistratie>
											<brp:actieInhoud>447</brp:actieInhoud>
											<brp:datumAanvangGeldigheid>2010-02-01</brp:datumAanvangGeldigheid>
											<brp:code>M</brp:code>
										</brp:geslachtsaanduiding>
									</brp:persoon>
								</brp:partner>
							</brp:betrokkenheden>
						</brp:huwelijk>
					</brp:partner>
				</brp:betrokkenheden>
				<brp:reisdocumenten>
					<brp:reisdocument brp:voorkomenSleutel="43" brp:objectSleutel="43" brp:objecttype="PersoonReisdocument">
						<brp:tijdstipRegistratie>2009-08-03T01:00:00.000Z</brp:tijdstipRegistratie>
						<brp:actieInhoud>455</brp:actieInhoud>
						<brp:soortCode>PN</brp:soortCode>
						<brp:nummer>NA4351785</brp:nummer>
						<brp:autoriteitVanAfgifte>B0385</brp:autoriteitVanAfgifte>
						<brp:datumIngangDocument>2008-02-29</brp:datumIngangDocument>
						<brp:datumEindeDocument>2013-02-28</brp:datumEindeDocument>
						<brp:datumUitgifte>2008-02-29</brp:datumUitgifte>
						<brp:datumInhoudingVermissing>2009-08-03</brp:datumInhoudingVermissing>
						<brp:aanduidingInhoudingVermissingCode>I</brp:aanduidingInhoudingVermissingCode>
					</brp:reisdocument>
				</brp:reisdocumenten>
				<brp:persoonskaart brp:voorkomenSleutel="40">
					<brp:tijdstipRegistratie>2011-05-12T01:00:00.000Z</brp:tijdstipRegistratie>
					<brp:actieInhoud>448</brp:actieInhoud>
					<brp:partijCode>020701</brp:partijCode>
					<brp:indicatieVolledigGeconverteerd>J</brp:indicatieVolledigGeconverteerd>
				</brp:persoonskaart>
				<brp:onderzoeken>
					<brp:onderzoek brp:objectSleutel="4" brp:objecttype="Onderzoek">
						<brp:onderzoek brp:voorkomenSleutel="4">
							<brp:tijdstipRegistratie>2011-05-12T12:35:00.000Z</brp:tijdstipRegistratie>
							<brp:actieInhoud>460</brp:actieInhoud>
							<brp:datumAanvang>2011-04-01</brp:datumAanvang>
						</brp:onderzoek>
						<brp:gegevensInOnderzoek>
							<brp:gegevenInOnderzoek brp:objectSleutel="29" brp:objecttype="GegevenInOnderzoek">
								<brp:tijdstipRegistratie>2011-05-12T12:35:00.000Z</brp:tijdstipRegistratie>
								<brp:actieInhoud>460</brp:actieInhoud>
								<brp:elementNaam>Persoon.Voornaam.Naam</brp:elementNaam>
								<brp:voorkomenSleutelGegeven>66</brp:voorkomenSleutelGegeven>
							</brp:gegevenInOnderzoek>
							<brp:gegevenInOnderzoek brp:objectSleutel="28" brp:objecttype="GegevenInOnderzoek">
								<brp:tijdstipRegistratie>2011-05-12T12:35:00.000Z</brp:tijdstipRegistratie>
								<brp:actieInhoud>460</brp:actieInhoud>
								<brp:elementNaam>Persoon.Geslachtsnaamcomponent.Stam</brp:elementNaam>
								<brp:voorkomenSleutelGegeven>50</brp:voorkomenSleutelGegeven>
							</brp:gegevenInOnderzoek>
							<brp:gegevenInOnderzoek brp:objectSleutel="27" brp:objecttype="GegevenInOnderzoek">
								<brp:tijdstipRegistratie>2011-05-12T12:35:00.000Z</brp:tijdstipRegistratie>
								<brp:actieInhoud>460</brp:actieInhoud>
								<brp:elementNaam>Persoon.Naamgebruik.Voornamen</brp:elementNaam>
								<brp:voorkomenSleutelGegeven>50</brp:voorkomenSleutelGegeven>
							</brp:gegevenInOnderzoek>
							<brp:gegevenInOnderzoek brp:objectSleutel="26" brp:objecttype="GegevenInOnderzoek">
								<brp:tijdstipRegistratie>2011-05-12T12:35:00.000Z</brp:tijdstipRegistratie>
								<brp:actieInhoud>460</brp:actieInhoud>
								<brp:elementNaam>Persoon.Naamgebruik.Geslachtsnaamstam</brp:elementNaam>
								<brp:voorkomenSleutelGegeven>50</brp:voorkomenSleutelGegeven>
							</brp:gegevenInOnderzoek>
							<brp:gegevenInOnderzoek brp:objectSleutel="25" brp:objecttype="GegevenInOnderzoek">
								<brp:tijdstipRegistratie>2011-05-12T12:35:00.000Z</brp:tijdstipRegistratie>
								<brp:actieInhoud>460</brp:actieInhoud>
								<brp:elementNaam>Persoon.SamengesteldeNaam.Voornamen</brp:elementNaam>
								<brp:voorkomenSleutelGegeven>167</brp:voorkomenSleutelGegeven>
							</brp:gegevenInOnderzoek>
							<brp:gegevenInOnderzoek brp:objectSleutel="24" brp:objecttype="GegevenInOnderzoek">
								<brp:tijdstipRegistratie>2011-05-12T12:35:00.000Z</brp:tijdstipRegistratie>
								<brp:actieInhoud>460</brp:actieInhoud>
								<brp:elementNaam>Persoon.SamengesteldeNaam.Geslachtsnaamstam</brp:elementNaam>
								<brp:voorkomenSleutelGegeven>167</brp:voorkomenSleutelGegeven>
							</brp:gegevenInOnderzoek>
						</brp:gegevensInOnderzoek>
					</brp:onderzoek>
					<brp:onderzoek brp:objectSleutel="5" brp:objecttype="Onderzoek">
						<brp:onderzoek brp:voorkomenSleutel="5">
							<brp:tijdstipRegistratie>2011-05-12T12:35:00.000Z</brp:tijdstipRegistratie>
							<brp:actieInhoud>461</brp:actieInhoud>
							<brp:datumAanvang>2011-04-01</brp:datumAanvang>
							<brp:datumEinde>2011-05-12</brp:datumEinde>
						</brp:onderzoek>
						<brp:gegevensInOnderzoek>
							<brp:gegevenInOnderzoek brp:objectSleutel="38" brp:objecttype="GegevenInOnderzoek">
								<brp:tijdstipRegistratie>2011-05-12T12:35:00.000Z</brp:tijdstipRegistratie>
								<brp:actieInhoud>461</brp:actieInhoud>
								<brp:elementNaam>Persoon.Adres.DatumAanvangGeldigheid</brp:elementNaam>
								<brp:voorkomenSleutelGegeven>121</brp:voorkomenSleutelGegeven>
							</brp:gegevenInOnderzoek>
							<brp:gegevenInOnderzoek brp:objectSleutel="37" brp:objecttype="GegevenInOnderzoek">
								<brp:tijdstipRegistratie>2011-05-12T12:35:00.000Z</brp:tijdstipRegistratie>
								<brp:actieInhoud>461</brp:actieInhoud>
								<brp:elementNaam>Persoon.Adres.Postcode</brp:elementNaam>
								<brp:voorkomenSleutelGegeven>121</brp:voorkomenSleutelGegeven>
							</brp:gegevenInOnderzoek>
							<brp:gegevenInOnderzoek brp:objectSleutel="36" brp:objecttype="GegevenInOnderzoek">
								<brp:tijdstipRegistratie>2011-05-12T12:35:00.000Z</brp:tijdstipRegistratie>
								<brp:actieInhoud>461</brp:actieInhoud>
								<brp:elementNaam>Persoon.Adres.GemeenteCode</brp:elementNaam>
								<brp:voorkomenSleutelGegeven>121</brp:voorkomenSleutelGegeven>
							</brp:gegevenInOnderzoek>
							<brp:gegevenInOnderzoek brp:objectSleutel="35" brp:objecttype="GegevenInOnderzoek">
								<brp:tijdstipRegistratie>2011-05-12T12:35:00.000Z</brp:tijdstipRegistratie>
								<brp:actieInhoud>461</brp:actieInhoud>
								<brp:elementNaam>Persoon.Adres.AfgekorteNaamOpenbareRuimte</brp:elementNaam>
								<brp:voorkomenSleutelGegeven>121</brp:voorkomenSleutelGegeven>
							</brp:gegevenInOnderzoek>
							<brp:gegevenInOnderzoek brp:objectSleutel="34" brp:objecttype="GegevenInOnderzoek">
								<brp:tijdstipRegistratie>2011-05-12T12:35:00.000Z</brp:tijdstipRegistratie>
								<brp:actieInhoud>461</brp:actieInhoud>
								<brp:elementNaam>Persoon.Adres.Huisnummer</brp:elementNaam>
								<brp:voorkomenSleutelGegeven>121</brp:voorkomenSleutelGegeven>
							</brp:gegevenInOnderzoek>
							<brp:gegevenInOnderzoek brp:objectSleutel="33" brp:objecttype="GegevenInOnderzoek">
								<brp:tijdstipRegistratie>2011-05-12T12:35:00.000Z</brp:tijdstipRegistratie>
								<brp:actieInhoud>461</brp:actieInhoud>
								<brp:elementNaam>Persoon.Adres.DatumAanvangAdreshouding</brp:elementNaam>
								<brp:voorkomenSleutelGegeven>121</brp:voorkomenSleutelGegeven>
							</brp:gegevenInOnderzoek>
							<brp:gegevenInOnderzoek brp:objectSleutel="32" brp:objecttype="GegevenInOnderzoek">
								<brp:tijdstipRegistratie>2011-05-12T12:35:00.000Z</brp:tijdstipRegistratie>
								<brp:actieInhoud>461</brp:actieInhoud>
								<brp:elementNaam>Persoon.Adres.SoortCode</brp:elementNaam>
								<brp:voorkomenSleutelGegeven>121</brp:voorkomenSleutelGegeven>
							</brp:gegevenInOnderzoek>
							<brp:gegevenInOnderzoek brp:objectSleutel="31" brp:objecttype="GegevenInOnderzoek">
								<brp:tijdstipRegistratie>2011-05-12T12:35:00.000Z</brp:tijdstipRegistratie>
								<brp:actieInhoud>461</brp:actieInhoud>
								<brp:elementNaam>Persoon.Bijhouding.DatumAanvangGeldigheid</brp:elementNaam>
								<brp:voorkomenSleutelGegeven>128</brp:voorkomenSleutelGegeven>
							</brp:gegevenInOnderzoek>
							<brp:gegevenInOnderzoek brp:objectSleutel="30" brp:objecttype="GegevenInOnderzoek">
								<brp:tijdstipRegistratie>2011-05-12T12:35:00.000Z</brp:tijdstipRegistratie>
								<brp:actieInhoud>461</brp:actieInhoud>
								<brp:elementNaam>Persoon.Bijhouding.PartijCode</brp:elementNaam>
								<brp:voorkomenSleutelGegeven>128</brp:voorkomenSleutelGegeven>
							</brp:gegevenInOnderzoek>
						</brp:gegevensInOnderzoek>
					</brp:onderzoek>
					<brp:onderzoek brp:objectSleutel="6" brp:objecttype="Onderzoek">
						<brp:onderzoek brp:voorkomenSleutel="6">
							<brp:tijdstipRegistratie>2011-05-12T12:35:00.000Z</brp:tijdstipRegistratie>
							<brp:actieInhoud>462</brp:actieInhoud>
							<brp:datumAanvang>2011-04-01</brp:datumAanvang>
						</brp:onderzoek>
						<brp:gegevensInOnderzoek>
							<brp:gegevenInOnderzoek brp:objectSleutel="39" brp:objecttype="GegevenInOnderzoek">
								<brp:tijdstipRegistratie>2011-05-12T12:35:00.000Z</brp:tijdstipRegistratie>
								<brp:actieInhoud>462</brp:actieInhoud>
								<brp:elementNaam>Persoon.Nationaliteit.RedenVerkrijgingCode</brp:elementNaam>
								<brp:voorkomenSleutelGegeven>43</brp:voorkomenSleutelGegeven>
							</brp:gegevenInOnderzoek>
						</brp:gegevensInOnderzoek>
					</brp:onderzoek>
					<brp:onderzoek brp:objectSleutel="7" brp:objecttype="Onderzoek">
						<brp:onderzoek brp:voorkomenSleutel="7">
							<brp:tijdstipRegistratie>2011-05-12T12:35:00.000Z</brp:tijdstipRegistratie>
							<brp:actieInhoud>463</brp:actieInhoud>
							<brp:datumAanvang>2011-04-01</brp:datumAanvang>
						</brp:onderzoek>
						<brp:gegevensInOnderzoek>
							<brp:gegevenInOnderzoek brp:objectSleutel="40" brp:objecttype="GegevenInOnderzoek">
								<brp:tijdstipRegistratie>2011-05-12T12:35:00.000Z</brp:tijdstipRegistratie>
								<brp:actieInhoud>463</brp:actieInhoud>
								<brp:elementNaam>Persoon.Indicatie.SignaleringMetBetrekkingTotVerstrekkenReisdocument.Waarde</brp:elementNaam>
								<brp:voorkomenSleutelGegeven>7</brp:voorkomenSleutelGegeven>
							</brp:gegevenInOnderzoek>
						</brp:gegevensInOnderzoek>
					</brp:onderzoek>
					<brp:onderzoek brp:objectSleutel="8" brp:objecttype="Onderzoek">
						<brp:onderzoek brp:voorkomenSleutel="8">
							<brp:tijdstipRegistratie>2011-05-12T12:35:00.000Z</brp:tijdstipRegistratie>
							<brp:actieInhoud>464</brp:actieInhoud>
							<brp:datumAanvang>2011-04-01</brp:datumAanvang>
						</brp:onderzoek>
						<brp:gegevensInOnderzoek>
							<brp:gegevenInOnderzoek brp:objectSleutel="41" brp:objecttype="GegevenInOnderzoek">
								<brp:tijdstipRegistratie>2011-05-12T12:35:00.000Z</brp:tijdstipRegistratie>
								<brp:actieInhoud>464</brp:actieInhoud>
								<brp:elementNaam>Persoon.Indicatie.OnderCuratele.Waarde</brp:elementNaam>
								<brp:voorkomenSleutelGegeven>8</brp:voorkomenSleutelGegeven>
							</brp:gegevenInOnderzoek>
						</brp:gegevensInOnderzoek>
					</brp:onderzoek>
					<brp:onderzoek brp:objectSleutel="9" brp:objecttype="Onderzoek">
						<brp:onderzoek brp:voorkomenSleutel="9">
							<brp:tijdstipRegistratie>2011-05-12T12:35:00.000Z</brp:tijdstipRegistratie>
							<brp:actieInhoud>465</brp:actieInhoud>
							<brp:datumAanvang>2011-04-01</brp:datumAanvang>
						</brp:onderzoek>
						<brp:gegevensInOnderzoek>
							<brp:gegevenInOnderzoek brp:objectSleutel="46" brp:objecttype="GegevenInOnderzoek">
								<brp:tijdstipRegistratie>2011-05-12T12:35:00.000Z</brp:tijdstipRegistratie>
								<brp:actieInhoud>465</brp:actieInhoud>
								<brp:elementNaam>Huwelijk.RedenEindeCode</brp:elementNaam>
								<brp:voorkomenSleutelGegeven>89</brp:voorkomenSleutelGegeven>
							</brp:gegevenInOnderzoek>
							<brp:gegevenInOnderzoek brp:objectSleutel="45" brp:objecttype="GegevenInOnderzoek">
								<brp:tijdstipRegistratie>2011-05-12T12:35:00.000Z</brp:tijdstipRegistratie>
								<brp:actieInhoud>465</brp:actieInhoud>
								<brp:elementNaam>Huwelijk.LandGebiedEindeCode</brp:elementNaam>
								<brp:voorkomenSleutelGegeven>89</brp:voorkomenSleutelGegeven>
							</brp:gegevenInOnderzoek>
							<brp:gegevenInOnderzoek brp:objectSleutel="44" brp:objecttype="GegevenInOnderzoek">
								<brp:tijdstipRegistratie>2011-05-12T12:35:00.000Z</brp:tijdstipRegistratie>
								<brp:actieInhoud>465</brp:actieInhoud>
								<brp:elementNaam>Huwelijk.GemeenteEindeCode</brp:elementNaam>
								<brp:voorkomenSleutelGegeven>89</brp:voorkomenSleutelGegeven>
							</brp:gegevenInOnderzoek>
							<brp:gegevenInOnderzoek brp:objectSleutel="43" brp:objecttype="GegevenInOnderzoek">
								<brp:tijdstipRegistratie>2011-05-12T12:35:00.000Z</brp:tijdstipRegistratie>
								<brp:actieInhoud>465</brp:actieInhoud>
								<brp:elementNaam>Huwelijk.DatumEinde</brp:elementNaam>
								<brp:voorkomenSleutelGegeven>89</brp:voorkomenSleutelGegeven>
							</brp:gegevenInOnderzoek>
						</brp:gegevensInOnderzoek>
					</brp:onderzoek>
					<brp:onderzoek brp:objectSleutel="10" brp:objecttype="Onderzoek">
						<brp:onderzoek brp:voorkomenSleutel="10">
							<brp:tijdstipRegistratie>2011-05-12T12:35:00.000Z</brp:tijdstipRegistratie>
							<brp:actieInhoud>466</brp:actieInhoud>
							<brp:datumAanvang>2011-04-01</brp:datumAanvang>
						</brp:onderzoek>
						<brp:gegevensInOnderzoek>
							<brp:gegevenInOnderzoek brp:objectSleutel="55" brp:objecttype="GegevenInOnderzoek">
								<brp:tijdstipRegistratie>2011-05-12T12:35:00.000Z</brp:tijdstipRegistratie>
								<brp:actieInhoud>466</brp:actieInhoud>
								<brp:elementNaam>GerelateerdeKind.Persoon.Geboorte.GemeenteCode</brp:elementNaam>
								<brp:voorkomenSleutelGegeven>158</brp:voorkomenSleutelGegeven>
							</brp:gegevenInOnderzoek>
							<brp:gegevenInOnderzoek brp:objectSleutel="54" brp:objecttype="GegevenInOnderzoek">
								<brp:tijdstipRegistratie>2011-05-12T12:35:00.000Z</brp:tijdstipRegistratie>
								<brp:actieInhoud>466</brp:actieInhoud>
								<brp:elementNaam>GerelateerdeKind.Persoon.Geboorte.LandGebiedCode</brp:elementNaam>
								<brp:voorkomenSleutelGegeven>158</brp:voorkomenSleutelGegeven>
							</brp:gegevenInOnderzoek>
							<brp:gegevenInOnderzoek brp:objectSleutel="53" brp:objecttype="GegevenInOnderzoek">
								<brp:tijdstipRegistratie>2011-05-12T12:35:00.000Z</brp:tijdstipRegistratie>
								<brp:actieInhoud>466</brp:actieInhoud>
								<brp:elementNaam>GerelateerdeKind.Persoon.Geboorte.Datum</brp:elementNaam>
								<brp:voorkomenSleutelGegeven>158</brp:voorkomenSleutelGegeven>
							</brp:gegevenInOnderzoek>
							<brp:gegevenInOnderzoek brp:objectSleutel="52" brp:objecttype="GegevenInOnderzoek">
								<brp:tijdstipRegistratie>2011-05-12T12:35:00.000Z</brp:tijdstipRegistratie>
								<brp:actieInhoud>466</brp:actieInhoud>
								<brp:elementNaam>GerelateerdeKind.Persoon.SamengesteldeNaam.DatumAanvangGeldigheid</brp:elementNaam>
								<brp:voorkomenSleutelGegeven>166</brp:voorkomenSleutelGegeven>
							</brp:gegevenInOnderzoek>
							<brp:gegevenInOnderzoek brp:objectSleutel="51" brp:objecttype="GegevenInOnderzoek">
								<brp:tijdstipRegistratie>2011-05-12T12:35:00.000Z</brp:tijdstipRegistratie>
								<brp:actieInhoud>466</brp:actieInhoud>
								<brp:elementNaam>GerelateerdeKind.Persoon.SamengesteldeNaam.Voornamen</brp:elementNaam>
								<brp:voorkomenSleutelGegeven>166</brp:voorkomenSleutelGegeven>
							</brp:gegevenInOnderzoek>
							<brp:gegevenInOnderzoek brp:objectSleutel="50" brp:objecttype="GegevenInOnderzoek">
								<brp:tijdstipRegistratie>2011-05-12T12:35:00.000Z</brp:tijdstipRegistratie>
								<brp:actieInhoud>466</brp:actieInhoud>
								<brp:elementNaam>GerelateerdeKind.Persoon.SamengesteldeNaam.Geslachtsnaamstam</brp:elementNaam>
								<brp:voorkomenSleutelGegeven>166</brp:voorkomenSleutelGegeven>
							</brp:gegevenInOnderzoek>
							<brp:gegevenInOnderzoek brp:objectSleutel="49" brp:objecttype="GegevenInOnderzoek">
								<brp:tijdstipRegistratie>2011-05-12T12:35:00.000Z</brp:tijdstipRegistratie>
								<brp:actieInhoud>466</brp:actieInhoud>
								<brp:elementNaam>GerelateerdeKind.Persoon.Identificatienummers.DatumAanvangGeldigheid</brp:elementNaam>
								<brp:voorkomenSleutelGegeven>96</brp:voorkomenSleutelGegeven>
							</brp:gegevenInOnderzoek>
							<brp:gegevenInOnderzoek brp:objectSleutel="48" brp:objecttype="GegevenInOnderzoek">
								<brp:tijdstipRegistratie>2011-05-12T12:35:00.000Z</brp:tijdstipRegistratie>
								<brp:actieInhoud>466</brp:actieInhoud>
								<brp:elementNaam>GerelateerdeKind.Persoon.Identificatienummers.Burgerservicenummer</brp:elementNaam>
								<brp:voorkomenSleutelGegeven>96</brp:voorkomenSleutelGegeven>
							</brp:gegevenInOnderzoek>
							<brp:gegevenInOnderzoek brp:objectSleutel="47" brp:objecttype="GegevenInOnderzoek">
								<brp:tijdstipRegistratie>2011-05-12T12:35:00.000Z</brp:tijdstipRegistratie>
								<brp:actieInhoud>466</brp:actieInhoud>
								<brp:elementNaam>GerelateerdeKind.Persoon.Identificatienummers.Administratienummer</brp:elementNaam>
								<brp:voorkomenSleutelGegeven>96</brp:voorkomenSleutelGegeven>
							</brp:gegevenInOnderzoek>
						</brp:gegevensInOnderzoek>
					</brp:onderzoek>
				</brp:onderzoeken>
				<brp:administratieveHandelingen>
					<brp:administratieveHandeling brp:objecttype="AdministratieveHandeling" brp:objectSleutel="40">
						<brp:soortNaam>GBA - Initiele vulling</brp:soortNaam>
						<brp:categorieNaam>GBA - Initiële vulling</brp:categorieNaam>
						<brp:partijCode>199902</brp:partijCode>
						<brp:tijdstipRegistratie>2017-02-08T11:31:58.152Z</brp:tijdstipRegistratie>
						<brp:bronnen>
							<brp:bron brp:objecttype="AdministratieveHandelingBron" brp:objectSleutel="247" brp:communicatieID="document247">
								<brp:document brp:objecttype="Document" brp:objectSleutel="247" brp:voorkomenSleutel="247">
									<brp:soortNaam>Historie conversie</brp:soortNaam>
									<brp:aktenummer>30B1017</brp:aktenummer>
									<brp:partijCode>038501</brp:partijCode>
								</brp:document>
							</brp:bron>
							<brp:bron brp:objecttype="AdministratieveHandelingBron" brp:objectSleutel="249" brp:communicatieID="document249">
								<brp:document brp:objecttype="Document" brp:objectSleutel="249" brp:voorkomenSleutel="249">
									<brp:soortNaam>Historie conversie</brp:soortNaam>
									<brp:omschrijving>signaleringslijst</brp:omschrijving>
									<brp:partijCode>000001</brp:partijCode>
								</brp:document>
							</brp:bron>
							<brp:bron brp:objecttype="AdministratieveHandelingBron" brp:objectSleutel="250" brp:communicatieID="document250">
								<brp:document brp:objecttype="Document" brp:objectSleutel="250" brp:voorkomenSleutel="250">
									<brp:soortNaam>Historie conversie</brp:soortNaam>
									<brp:omschrijving>kennisgeving curateleregister</brp:omschrijving>
									<brp:partijCode>038501</brp:partijCode>
								</brp:document>
							</brp:bron>
							<brp:bron brp:objecttype="AdministratieveHandelingBron" brp:objectSleutel="251" brp:communicatieID="document251">
								<brp:document brp:objecttype="Document" brp:objectSleutel="251" brp:voorkomenSleutel="251">
									<brp:soortNaam>Historie conversie</brp:soortNaam>
									<brp:omschrijving>Aanvraagformulier</brp:omschrijving>
									<brp:partijCode>038501</brp:partijCode>
								</brp:document>
							</brp:bron>
							<brp:bron brp:objecttype="AdministratieveHandelingBron" brp:objectSleutel="255" brp:communicatieID="document255">
								<brp:document brp:objecttype="Document" brp:objectSleutel="255" brp:voorkomenSleutel="255">
									<brp:soortNaam>Historie conversie</brp:soortNaam>
									<brp:omschrijving>PL gerelateerde</brp:omschrijving>
									<brp:partijCode>021801</brp:partijCode>
								</brp:document>
							</brp:bron>
							<brp:bron brp:objecttype="AdministratieveHandelingBron" brp:objectSleutel="254" brp:communicatieID="document254">
								<brp:document brp:objecttype="Document" brp:objectSleutel="254" brp:voorkomenSleutel="254">
									<brp:soortNaam>Historie conversie</brp:soortNaam>
									<brp:aktenummer>10A0718</brp:aktenummer>
									<brp:partijCode>021801</brp:partijCode>
								</brp:document>
							</brp:bron>
							<brp:bron brp:objecttype="AdministratieveHandelingBron"	brp:objectSleutel="252" brp:communicatieID="document252">
								<brp:document brp:objecttype="Document" brp:objectSleutel="252" brp:voorkomenSleutel="252">
									<brp:soortNaam>Historie conversie</brp:soortNaam>
									<brp:aktenummer>30A1017</brp:aktenummer>
									<brp:partijCode>021801</brp:partijCode>
								</brp:document>
							</brp:bron>
							<brp:bron brp:objecttype="AdministratieveHandelingBron"	brp:objectSleutel="248" brp:communicatieID="document248">
								<brp:document brp:objecttype="Document" brp:objectSleutel="248" brp:voorkomenSleutel="248">
									<brp:soortNaam>Historie conversie</brp:soortNaam>
									<brp:omschrijving>PKA</brp:omschrijving>
									<brp:partijCode>020701</brp:partijCode>
								</brp:document>
							</brp:bron>
							<brp:bron brp:objecttype="AdministratieveHandelingBron" brp:objectSleutel="253" brp:communicatieID="document253">
								<brp:document brp:objecttype="Document" brp:objectSleutel="253" brp:voorkomenSleutel="253">
									<brp:soortNaam>Historie conversie</brp:soortNaam>
									<brp:omschrijving>PK</brp:omschrijving>
									<brp:partijCode>020701</brp:partijCode>
								</brp:document>
							</brp:bron>
						</brp:bronnen>
						<brp:bijgehoudenActies>
							<brp:actie brp:objecttype="Actie" brp:objectSleutel="460">
								<brp:soortNaam>Conversie GBA</brp:soortNaam>
								<brp:partijCode>199902</brp:partijCode>
							</brp:actie>
							<brp:actie brp:objecttype="Actie" brp:objectSleutel="461">
								<brp:soortNaam>Conversie GBA</brp:soortNaam>
								<brp:partijCode>199902</brp:partijCode>
							</brp:actie>
							<brp:actie brp:objecttype="Actie" brp:objectSleutel="462">
								<brp:soortNaam>Conversie GBA</brp:soortNaam>
								<brp:partijCode>199902</brp:partijCode>
							</brp:actie>
							<brp:actie brp:objecttype="Actie" brp:objectSleutel="463">
								<brp:soortNaam>Conversie GBA</brp:soortNaam>
								<brp:partijCode>199902</brp:partijCode>
							</brp:actie>
							<brp:actie brp:objecttype="Actie" brp:objectSleutel="464">
								<brp:soortNaam>Conversie GBA</brp:soortNaam>
								<brp:partijCode>199902</brp:partijCode>
							</brp:actie>
							<brp:actie brp:objecttype="Actie" brp:objectSleutel="465">
								<brp:soortNaam>Conversie GBA</brp:soortNaam>
								<brp:partijCode>199902</brp:partijCode>
							</brp:actie>
							<brp:actie brp:objecttype="Actie" brp:objectSleutel="466">
								<brp:soortNaam>Conversie GBA</brp:soortNaam>
								<brp:partijCode>199902</brp:partijCode>
							</brp:actie>
							<brp:actie brp:objecttype="Actie" brp:objectSleutel="448">
								<brp:soortNaam>Conversie GBA</brp:soortNaam>
								<brp:partijCode>199902</brp:partijCode>
							</brp:actie>
							<brp:actie brp:objecttype="Actie" brp:objectSleutel="447">
								<brp:soortNaam>Conversie GBA</brp:soortNaam>
								<brp:partijCode>199902</brp:partijCode>
								<brp:bronnen>
									<brp:bron brp:objecttype="ActieBron" brp:objectSleutel="247" brp:referentieID="document247"/>
								</brp:bronnen>
							</brp:actie>
							<brp:actie brp:objecttype="Actie" brp:objectSleutel="453">
								<brp:soortNaam>Conversie GBA</brp:soortNaam>
								<brp:partijCode>199902</brp:partijCode>
								<brp:datumOntlening>0000</brp:datumOntlening>
								<brp:bronnen>
									<brp:bron brp:objecttype="ActieBron" brp:objectSleutel="249" brp:referentieID="document249"/>
								</brp:bronnen>
							</brp:actie>
							<brp:actie brp:objecttype="Actie" brp:objectSleutel="454">
								<brp:soortNaam>Conversie GBA</brp:soortNaam>
								<brp:partijCode>199902</brp:partijCode>
								<brp:datumOntlening>2009-08-03</brp:datumOntlening>
								<brp:bronnen>
									<brp:bron brp:objecttype="ActieBron" brp:objectSleutel="250" brp:referentieID="document250"/>
								</brp:bronnen>
							</brp:actie>
							<brp:actie brp:objecttype="Actie" brp:objectSleutel="455">
								<brp:soortNaam>Conversie GBA</brp:soortNaam>
								<brp:partijCode>199902</brp:partijCode>
								<brp:datumOntlening>2008-02-29</brp:datumOntlening>
								<brp:bronnen>
									<brp:bron brp:objecttype="ActieBron" brp:objectSleutel="251" brp:referentieID="document251"/>
								</brp:bronnen>
							</brp:actie>
							<brp:actie brp:objecttype="Actie" brp:objectSleutel="450">
								<brp:soortNaam>Conversie GBA</brp:soortNaam>
								<brp:partijCode>199902</brp:partijCode>
							</brp:actie>
							<brp:actie brp:objecttype="Actie" brp:objectSleutel="459">
								<brp:soortNaam>Conversie GBA</brp:soortNaam>
								<brp:partijCode>199902</brp:partijCode>
								<brp:datumOntlening>1999-07-29</brp:datumOntlening>
								<brp:bronnen>
									<brp:bron brp:objecttype="ActieBron" brp:objectSleutel="255" brp:referentieID="document255"/>
								</brp:bronnen>
							</brp:actie>
							<brp:actie brp:objecttype="Actie" brp:objectSleutel="458">
								<brp:soortNaam>Conversie GBA</brp:soortNaam>
								<brp:partijCode>199902</brp:partijCode>
								<brp:bronnen>
									<brp:bron brp:objecttype="ActieBron" brp:objectSleutel="254" brp:referentieID="document254"/>
								</brp:bronnen>
							</brp:actie>
							<brp:actie brp:objecttype="Actie" brp:objectSleutel="456">
								<brp:soortNaam>Conversie GBA</brp:soortNaam>
								<brp:partijCode>199902</brp:partijCode>
								<brp:bronnen>
									<brp:bron brp:objecttype="ActieBron" brp:objectSleutel="252" brp:referentieID="document252"/>
								</brp:bronnen>
							</brp:actie>
							<brp:actie brp:objecttype="Actie" brp:objectSleutel="449">
								<brp:soortNaam>Conversie GBA</brp:soortNaam>
								<brp:partijCode>199902</brp:partijCode>
								<brp:datumOntlening>1994-05-01</brp:datumOntlening>
								<brp:bronnen>
									<brp:bron brp:objecttype="ActieBron" brp:objectSleutel="248" brp:referentieID="document248"/>
								</brp:bronnen>
							</brp:actie>
							<brp:actie brp:objecttype="Actie" brp:objectSleutel="451">
								<brp:soortNaam>Conversie GBA</brp:soortNaam>
								<brp:partijCode>199902</brp:partijCode>
							</brp:actie>
							<brp:actie brp:objecttype="Actie" brp:objectSleutel="452">
								<brp:soortNaam>Conversie GBA</brp:soortNaam>
								<brp:partijCode>199902</brp:partijCode>
							</brp:actie>
							<brp:actie brp:objecttype="Actie" brp:objectSleutel="457">
								<brp:soortNaam>Conversie GBA</brp:soortNaam>
								<brp:partijCode>199902</brp:partijCode>
								<brp:datumOntlening>1994-05-01</brp:datumOntlening>
								<brp:bronnen>
									<brp:bron brp:objecttype="ActieBron" brp:objectSleutel="253" brp:referentieID="document253"/>
								</brp:bronnen>
							</brp:actie>
						</brp:bijgehoudenActies>
					</brp:administratieveHandeling>
				</brp:administratieveHandelingen>
			</brp:persoon>
		</brp:geselecteerdePersoon>
		<brp:geselecteerdePersoon>
			<brp:persoon brp:objectSleutel="prZCT6U+/G1pnow2P0RwmV5dONoNEcwuVZNk2EVXAn4=" brp:objecttype="Persoon">
				<brp:soortCode>I</brp:soortCode>
				<brp:afgeleidAdministratief brp:voorkomenSleutel="12">
					<brp:tijdstipRegistratie>2011-01-17T01:00:00.000Z</brp:tijdstipRegistratie>
					<brp:actieInhoud>126</brp:actieInhoud>
					<brp:tijdstipLaatsteWijziging>2017-02-07T09:52:24.369Z</brp:tijdstipLaatsteWijziging>
					<brp:tijdstipLaatsteWijzigingGBASystematiek>2017-02-07T09:52:24.369Z</brp:tijdstipLaatsteWijzigingGBASystematiek>
				</brp:afgeleidAdministratief>
				<brp:identificatienummers brp:voorkomenSleutel="32">
					<brp:tijdstipRegistratie>1995-10-01T01:00:00.000Z</brp:tijdstipRegistratie>
					<brp:actieInhoud>127</brp:actieInhoud>
					<brp:datumAanvangGeldigheid>1991-06-07</brp:datumAanvangGeldigheid>
					<brp:burgerservicenummer>117664005</brp:burgerservicenummer>
					<brp:administratienummer>1401026379</brp:administratienummer>
				</brp:identificatienummers>
				<brp:identificatienummers brp:voorkomenSleutel="31">
					<brp:tijdstipRegistratie>1994-03-10T01:00:00.000Z</brp:tijdstipRegistratie>
					<brp:actieInhoud>128</brp:actieInhoud>
					<brp:datumAanvangGeldigheid>1990-06-07</brp:datumAanvangGeldigheid>
					<brp:datumEindeGeldigheid>1991-06-07</brp:datumEindeGeldigheid>
					<brp:actieAanpassingGeldigheid>127</brp:actieAanpassingGeldigheid>
					<brp:administratienummer>1401026379</brp:administratienummer>
				</brp:identificatienummers>
				<brp:samengesteldeNaam brp:voorkomenSleutel="52">
					<brp:tijdstipRegistratie>1995-10-01T01:00:00.000Z</brp:tijdstipRegistratie>
					<brp:actieInhoud>127</brp:actieInhoud>
					<brp:datumAanvangGeldigheid>1991-06-07</brp:datumAanvangGeldigheid>
					<brp:indicatieAfgeleid>J</brp:indicatieAfgeleid>
					<brp:indicatieNamenreeks>N</brp:indicatieNamenreeks>
					<brp:voornamen>Marjolein</brp:voornamen>
					<brp:voorvoegsel>de</brp:voorvoegsel>
					<brp:scheidingsteken> </brp:scheidingsteken>
					<brp:geslachtsnaamstam>Goede</brp:geslachtsnaamstam>
				</brp:samengesteldeNaam>
				<brp:samengesteldeNaam brp:voorkomenSleutel="51">
					<brp:tijdstipRegistratie>1994-03-10T01:00:00.000Z</brp:tijdstipRegistratie>
					<brp:actieInhoud>128</brp:actieInhoud>
					<brp:datumAanvangGeldigheid>1990-06-07</brp:datumAanvangGeldigheid>
					<brp:datumEindeGeldigheid>1991-06-07</brp:datumEindeGeldigheid>
					<brp:actieAanpassingGeldigheid>127</brp:actieAanpassingGeldigheid>
					<brp:indicatieAfgeleid>J</brp:indicatieAfgeleid>
					<brp:indicatieNamenreeks>N</brp:indicatieNamenreeks>
					<brp:voornamen>Marjolein</brp:voornamen>
					<brp:voorvoegsel>de</brp:voorvoegsel>
					<brp:scheidingsteken> </brp:scheidingsteken>
					<brp:geslachtsnaamstam>Verstotene</brp:geslachtsnaamstam>
				</brp:samengesteldeNaam>
				<brp:geboorte brp:voorkomenSleutel="50">
					<brp:tijdstipRegistratie>1995-10-01T01:00:00.000Z</brp:tijdstipRegistratie>
					<brp:actieInhoud>127</brp:actieInhoud>
					<brp:datum>1990-06-07</brp:datum>
					<brp:gemeenteCode>0385</brp:gemeenteCode>
					<brp:landGebiedCode>6030</brp:landGebiedCode>
				</brp:geboorte>
				<brp:geboorte brp:voorkomenSleutel="49">
					<brp:tijdstipRegistratie>1994-03-10T01:00:00.000Z</brp:tijdstipRegistratie>
					<brp:actieInhoud>128</brp:actieInhoud>
					<brp:tijdstipVerval>1994-03-10T01:00:00.000Z</brp:tijdstipVerval>
					<brp:actieVerval>128</brp:actieVerval>
					<brp:datum>1990-06-07</brp:datum>
					<brp:gemeenteCode>0385</brp:gemeenteCode>
					<brp:landGebiedCode>6030</brp:landGebiedCode>
				</brp:geboorte>
				<brp:geslachtsaanduiding brp:voorkomenSleutel="45">
					<brp:tijdstipRegistratie>1995-10-01T01:00:00.000Z</brp:tijdstipRegistratie>
					<brp:actieInhoud>127</brp:actieInhoud>
					<brp:datumAanvangGeldigheid>1991-06-07</brp:datumAanvangGeldigheid>
					<brp:code>V</brp:code>
				</brp:geslachtsaanduiding>
				<brp:geslachtsaanduiding brp:voorkomenSleutel="44">
					<brp:tijdstipRegistratie>1994-03-10T01:00:00.000Z</brp:tijdstipRegistratie>
					<brp:actieInhoud>128</brp:actieInhoud>
					<brp:datumAanvangGeldigheid>1990-06-07</brp:datumAanvangGeldigheid>
					<brp:datumEindeGeldigheid>1991-06-07</brp:datumEindeGeldigheid>
					<brp:actieAanpassingGeldigheid>127</brp:actieAanpassingGeldigheid>
					<brp:code>V</brp:code>
				</brp:geslachtsaanduiding>
				<brp:inschrijving brp:voorkomenSleutel="12">
					<brp:tijdstipRegistratie>2011-01-17T01:00:00.000Z</brp:tijdstipRegistratie>
					<brp:actieInhoud>126</brp:actieInhoud>
					<brp:datum>1994-03-10</brp:datum>
				</brp:inschrijving>
				<brp:bijhouding brp:voorkomenSleutel="32">
					<brp:tijdstipRegistratie>2009-09-06T01:00:00.000Z</brp:tijdstipRegistratie>
					<brp:actieInhoud>130</brp:actieInhoud>
					<brp:datumAanvangGeldigheid>1991-06-07</brp:datumAanvangGeldigheid>
					<brp:partijCode>038501</brp:partijCode>
					<brp:bijhoudingsaardCode>I</brp:bijhoudingsaardCode>
					<brp:nadereBijhoudingsaardCode>A</brp:nadereBijhoudingsaardCode>
				</brp:bijhouding>
				<brp:bijhouding brp:voorkomenSleutel="31">
					<brp:tijdstipRegistratie>1994-03-10T01:00:00.000Z</brp:tijdstipRegistratie>
					<brp:actieInhoud>129</brp:actieInhoud>
					<brp:tijdstipVerval>1994-03-10T01:00:00.000Z</brp:tijdstipVerval>
					<brp:actieVerval>129</brp:actieVerval>
					<brp:datumAanvangGeldigheid>1991-06-07</brp:datumAanvangGeldigheid>
					<brp:partijCode>038501</brp:partijCode>
					<brp:bijhoudingsaardCode>I</brp:bijhoudingsaardCode>
					<brp:nadereBijhoudingsaardCode>?</brp:nadereBijhoudingsaardCode>
				</brp:bijhouding>
				<brp:voornamen>
					<brp:voornaam brp:voorkomenSleutel="15" brp:objectSleutel="13" brp:objecttype="PersoonVoornaam">
						<brp:tijdstipRegistratie>1995-10-01T01:00:00.000Z</brp:tijdstipRegistratie>
						<brp:actieInhoud>127</brp:actieInhoud>
						<brp:datumAanvangGeldigheid>1991-06-07</brp:datumAanvangGeldigheid>
						<brp:volgnummer>1</brp:volgnummer>
						<brp:naam>Marjolein</brp:naam>
					</brp:voornaam>
					<brp:voornaam brp:voorkomenSleutel="14" brp:objectSleutel="13" brp:objecttype="PersoonVoornaam">
						<brp:tijdstipRegistratie>1994-03-10T01:00:00.000Z</brp:tijdstipRegistratie>
						<brp:actieInhoud>128</brp:actieInhoud>
						<brp:datumAanvangGeldigheid>1990-06-07</brp:datumAanvangGeldigheid>
						<brp:datumEindeGeldigheid>1991-06-07</brp:datumEindeGeldigheid>
						<brp:actieAanpassingGeldigheid>127</brp:actieAanpassingGeldigheid>
						<brp:volgnummer>1</brp:volgnummer>
						<brp:naam>Marjolein</brp:naam>
					</brp:voornaam>
				</brp:voornamen>
				<brp:geslachtsnaamcomponenten>
					<brp:geslachtsnaamcomponent brp:voorkomenSleutel="14" brp:objectSleutel="12" brp:objecttype="PersoonGeslachtsnaamcomponent">
						<brp:tijdstipRegistratie>1995-10-01T01:00:00.000Z</brp:tijdstipRegistratie>
						<brp:actieInhoud>127</brp:actieInhoud>
						<brp:datumAanvangGeldigheid>1991-06-07</brp:datumAanvangGeldigheid>
						<brp:volgnummer>1</brp:volgnummer>
						<brp:voorvoegsel>de</brp:voorvoegsel>
						<brp:scheidingsteken> </brp:scheidingsteken>
						<brp:stam>Goede</brp:stam>
					</brp:geslachtsnaamcomponent>
					<brp:geslachtsnaamcomponent brp:voorkomenSleutel="13" brp:objectSleutel="12" brp:objecttype="PersoonGeslachtsnaamcomponent">
						<brp:tijdstipRegistratie>1994-03-10T01:00:00.000Z</brp:tijdstipRegistratie>
						<brp:actieInhoud>128</brp:actieInhoud>
						<brp:datumAanvangGeldigheid>1990-06-07</brp:datumAanvangGeldigheid>
						<brp:datumEindeGeldigheid>1991-06-07</brp:datumEindeGeldigheid>
						<brp:actieAanpassingGeldigheid>127</brp:actieAanpassingGeldigheid>
						<brp:volgnummer>1</brp:volgnummer>
						<brp:voorvoegsel>de</brp:voorvoegsel>
						<brp:scheidingsteken> </brp:scheidingsteken>
						<brp:stam>Verstotene</brp:stam>
					</brp:geslachtsnaamcomponent>
				</brp:geslachtsnaamcomponenten>
				<brp:naamgebruik brp:voorkomenSleutel="14">
					<brp:tijdstipRegistratie>1995-10-01T01:00:00.000Z</brp:tijdstipRegistratie>
					<brp:actieInhoud>127</brp:actieInhoud>
					<brp:code>E</brp:code>
					<brp:indicatieAfgeleid>J</brp:indicatieAfgeleid>
					<brp:voornamen>Marjolein</brp:voornamen>
					<brp:voorvoegsel>de</brp:voorvoegsel>
					<brp:scheidingsteken> </brp:scheidingsteken>
					<brp:geslachtsnaamstam>Goede</brp:geslachtsnaamstam>
				</brp:naamgebruik>
				<brp:naamgebruik brp:voorkomenSleutel="13">
					<brp:tijdstipRegistratie>1994-03-10T01:00:00.000Z</brp:tijdstipRegistratie>
					<brp:actieInhoud>128</brp:actieInhoud>
					<brp:tijdstipVerval>1994-03-10T01:00:00.000Z</brp:tijdstipVerval>
					<brp:actieVerval>128</brp:actieVerval>
					<brp:code>E</brp:code>
					<brp:indicatieAfgeleid>J</brp:indicatieAfgeleid>
					<brp:voornamen>Marjolein</brp:voornamen>
					<brp:voorvoegsel>de</brp:voorvoegsel>
					<brp:scheidingsteken> </brp:scheidingsteken>
					<brp:geslachtsnaamstam>Verstotene</brp:geslachtsnaamstam>
				</brp:naamgebruik>
				<brp:adressen>
					<brp:adres brp:voorkomenSleutel="31" brp:objectSleutel="12" brp:objecttype="PersoonAdres">
						<brp:tijdstipRegistratie>2009-09-06T01:00:00.000Z</brp:tijdstipRegistratie>
						<brp:actieInhoud>130</brp:actieInhoud>
						<brp:datumAanvangGeldigheid>2009-09-06</brp:datumAanvangGeldigheid>
						<brp:soortCode>W</brp:soortCode>
						<brp:redenWijzigingCode>B</brp:redenWijzigingCode>
						<brp:datumAanvangAdreshouding>1991-06-07</brp:datumAanvangAdreshouding>
						<brp:identificatiecodeAdresseerbaarObject>0385010270021001</brp:identificatiecodeAdresseerbaarObject>
						<brp:identificatiecodeNummeraanduiding>0385200270021001</brp:identificatiecodeNummeraanduiding>
						<brp:gemeenteCode>0385</brp:gemeenteCode>
						<brp:naamOpenbareRuimte>Marktweg</brp:naamOpenbareRuimte>
						<brp:afgekorteNaamOpenbareRuimte>Marktweg</brp:afgekorteNaamOpenbareRuimte>
						<brp:huisnummer>21</brp:huisnummer>
						<brp:postcode>2525JA</brp:postcode>
						<brp:woonplaatsnaam>Schardam</brp:woonplaatsnaam>
						<brp:landGebiedCode>6030</brp:landGebiedCode>
					</brp:adres>
					<brp:adres brp:voorkomenSleutel="30" brp:objectSleutel="12" brp:objecttype="PersoonAdres">
						<brp:tijdstipRegistratie>1994-03-10T01:00:00.000Z</brp:tijdstipRegistratie>
						<brp:actieInhoud>129</brp:actieInhoud>
						<brp:datumAanvangGeldigheid>1991-06-07</brp:datumAanvangGeldigheid>
						<brp:datumEindeGeldigheid>2009-09-06</brp:datumEindeGeldigheid>
						<brp:actieAanpassingGeldigheid>130</brp:actieAanpassingGeldigheid>
						<brp:soortCode>W</brp:soortCode>
						<brp:redenWijzigingCode>A</brp:redenWijzigingCode>
						<brp:datumAanvangAdreshouding>1991-06-07</brp:datumAanvangAdreshouding>
						<brp:gemeenteCode>0385</brp:gemeenteCode>
						<brp:afgekorteNaamOpenbareRuimte>Marktweg</brp:afgekorteNaamOpenbareRuimte>
						<brp:huisnummer>21</brp:huisnummer>
						<brp:postcode>2525JA</brp:postcode>
						<brp:landGebiedCode>6030</brp:landGebiedCode>
					</brp:adres>
				</brp:adressen>
				<brp:nationaliteiten>
					<brp:nationaliteit brp:voorkomenSleutel="14" brp:objectSleutel="14" brp:objecttype="PersoonNationaliteit">
						<brp:tijdstipRegistratie>1994-03-15T01:00:00.000Z</brp:tijdstipRegistratie>
						<brp:actieInhoud>131</brp:actieInhoud>
						<brp:datumAanvangGeldigheid>1994-03-15</brp:datumAanvangGeldigheid>
						<brp:nationaliteitCode>0001</brp:nationaliteitCode>
						<brp:redenVerkrijgingCode>017</brp:redenVerkrijgingCode>
					</brp:nationaliteit>
					<brp:nationaliteit brp:voorkomenSleutel="15" brp:objectSleutel="15" brp:objecttype="PersoonNationaliteit">
						<brp:tijdstipRegistratie>1994-03-10T01:00:00.000Z</brp:tijdstipRegistratie>
						<brp:actieInhoud>132</brp:actieInhoud>
						<brp:tijdstipVerval>2015-01-31T01:00:00.000Z</brp:tijdstipVerval>
						<brp:actieVerval>133</brp:actieVerval>
						<brp:datumAanvangGeldigheid>1990-06-07</brp:datumAanvangGeldigheid>
						<brp:nationaliteitCode>0142</brp:nationaliteitCode>
						<brp:indicatieBijhoudingBeeindigd>J</brp:indicatieBijhoudingBeeindigd>
					</brp:nationaliteit>
				</brp:nationaliteiten>
				<brp:indicaties>
					<brp:derdeHeeftGezag brp:voorkomenSleutel="1" brp:objectSleutel="1" brp:objecttype="PersoonIndicatie">
						<brp:tijdstipRegistratie>1994-03-10T01:00:00.000Z</brp:tijdstipRegistratie>
						<brp:actieInhoud>135</brp:actieInhoud>
						<brp:datumAanvangGeldigheid>1991-06-07</brp:datumAanvangGeldigheid>
						<brp:datumEindeGeldigheid>1994-03-15</brp:datumEindeGeldigheid>
						<brp:actieAanpassingGeldigheid>134</brp:actieAanpassingGeldigheid>
						<brp:waarde>J</brp:waarde>
					</brp:derdeHeeftGezag>
				</brp:indicaties>
				<brp:betrokkenheden>
					<brp:kind brp:objectSleutel="64" brp:objecttype="Betrokkenheid" brp:voorkomenSleutel="67">
						<brp:tijdstipRegistratie>1994-03-15T01:00:00.000Z</brp:tijdstipRegistratie>
						<brp:actieInhoud>138</brp:actieInhoud>
						<brp:familierechtelijkeBetrekking brp:objectSleutel="27" brp:objecttype="Relatie">
							<brp:relatie brp:voorkomenSleutel="28">
								<brp:tijdstipRegistratie>1994-03-15T01:00:00.000Z</brp:tijdstipRegistratie>
								<brp:actieInhoud>138</brp:actieInhoud>
							</brp:relatie>
							<brp:betrokkenheden>
								<brp:ouder brp:objectSleutel="65" brp:objecttype="Betrokkenheid" brp:voorkomenSleutel="64">
									<brp:tijdstipRegistratie>1994-03-15T01:00:00.000Z</brp:tijdstipRegistratie>
									<brp:actieInhoud>138</brp:actieInhoud>
									<brp:persoon brp:objectSleutel="prZCT6U+/G3J7ik/h1Pu5ykqJH7oggYOVZNk2EVXAn4=" brp:objecttype="Persoon">
										<brp:soortCode>P</brp:soortCode>
										<brp:identificatienummers brp:voorkomenSleutel="29">
											<brp:tijdstipRegistratie>1995-10-01T01:00:00.000Z</brp:tijdstipRegistratie>
											<brp:actieInhoud>125</brp:actieInhoud>
											<brp:datumAanvangGeldigheid>1994-03-16</brp:datumAanvangGeldigheid>
											<brp:burgerservicenummer>116108873</brp:burgerservicenummer>
											<brp:administratienummer>1401025983</brp:administratienummer>
										</brp:identificatienummers>
										<brp:samengesteldeNaam brp:voorkomenSleutel="48">
											<brp:tijdstipRegistratie>1995-10-01T01:00:00.000Z</brp:tijdstipRegistratie>
											<brp:actieInhoud>125</brp:actieInhoud>
											<brp:datumAanvangGeldigheid>1994-03-16</brp:datumAanvangGeldigheid>
											<brp:indicatieAfgeleid>N</brp:indicatieAfgeleid>
											<brp:indicatieNamenreeks>N</brp:indicatieNamenreeks>
											<brp:voornamen>José</brp:voornamen>
											<brp:voorvoegsel>van 't</brp:voorvoegsel>
											<brp:scheidingsteken> </brp:scheidingsteken>
											<brp:geslachtsnaamstam>Wiel</brp:geslachtsnaamstam>
										</brp:samengesteldeNaam>
										<brp:geboorte brp:voorkomenSleutel="46">
											<brp:tijdstipRegistratie>1995-10-01T01:00:00.000Z</brp:tijdstipRegistratie>
											<brp:actieInhoud>125</brp:actieInhoud>
											<brp:datum>1971-01-07</brp:datum>
											<brp:gemeenteCode>0344</brp:gemeenteCode>
											<brp:landGebiedCode>6030</brp:landGebiedCode>
										</brp:geboorte>
										<brp:geslachtsaanduiding brp:voorkomenSleutel="41">
											<brp:tijdstipRegistratie>1995-10-01T01:00:00.000Z</brp:tijdstipRegistratie>
											<brp:actieInhoud>125</brp:actieInhoud>
											<brp:datumAanvangGeldigheid>1994-03-16</brp:datumAanvangGeldigheid>
											<brp:code>V</brp:code>
										</brp:geslachtsaanduiding>
									</brp:persoon>
									<brp:ouderschap brp:voorkomenSleutel="30">
										<brp:tijdstipRegistratie>1994-03-15T01:00:00.000Z</brp:tijdstipRegistratie>
										<brp:actieInhoud>138</brp:actieInhoud>
										<brp:datumAanvangGeldigheid>1991-06-07</brp:datumAanvangGeldigheid>
									</brp:ouderschap>
									<brp:ouderlijkGezag brp:voorkomenSleutel="1">
										<brp:tijdstipRegistratie>1994-03-10T01:00:00.000Z</brp:tijdstipRegistratie>
										<brp:actieInhoud>135</brp:actieInhoud>
										<brp:datumAanvangGeldigheid>1991-06-07</brp:datumAanvangGeldigheid>
										<brp:datumEindeGeldigheid>1994-03-15</brp:datumEindeGeldigheid>
										<brp:actieAanpassingGeldigheid>134</brp:actieAanpassingGeldigheid>
										<brp:indicatieOuderHeeftGezag>N</brp:indicatieOuderHeeftGezag>
									</brp:ouderlijkGezag>
								</brp:ouder>
								<brp:ouder brp:objectSleutel="66" brp:objecttype="Betrokkenheid" brp:voorkomenSleutel="65">
									<brp:tijdstipRegistratie>1994-03-10T01:00:00.000Z</brp:tijdstipRegistratie>
									<brp:actieInhoud>139</brp:actieInhoud>
									<brp:persoon brp:objectSleutel="prZCT6U+/G1bHf3Y52fzhCkqJH7oggYOVZNk2EVXAn4=" brp:objecttype="Persoon">
										<brp:soortCode>P</brp:soortCode>
										<brp:samengesteldeNaam brp:voorkomenSleutel="49">
											<brp:tijdstipRegistratie>1994-03-10T01:00:00.000Z</brp:tijdstipRegistratie>
											<brp:actieInhoud>139</brp:actieInhoud>
											<brp:datumAanvangGeldigheid>1990-06-07</brp:datumAanvangGeldigheid>
											<brp:indicatieAfgeleid>N</brp:indicatieAfgeleid>
											<brp:indicatieNamenreeks>N</brp:indicatieNamenreeks>
											<brp:voornamen>Alex</brp:voornamen>
											<brp:voorvoegsel>de</brp:voorvoegsel>
											<brp:scheidingsteken> </brp:scheidingsteken>
											<brp:geslachtsnaamstam>Verstotene</brp:geslachtsnaamstam>
										</brp:samengesteldeNaam>
										<brp:geboorte brp:voorkomenSleutel="47">
											<brp:tijdstipRegistratie>1994-03-10T01:00:00.000Z</brp:tijdstipRegistratie>
											<brp:actieInhoud>139</brp:actieInhoud>
											<brp:datum>1970-04-12</brp:datum>
											<brp:buitenlandsePlaats>Harare</brp:buitenlandsePlaats>
											<brp:landGebiedCode>5004</brp:landGebiedCode>
										</brp:geboorte>
										<brp:geslachtsaanduiding brp:voorkomenSleutel="42">
											<brp:tijdstipRegistratie>1994-03-10T01:00:00.000Z</brp:tijdstipRegistratie>
											<brp:actieInhoud>139</brp:actieInhoud>
											<brp:datumAanvangGeldigheid>1990-06-07</brp:datumAanvangGeldigheid>
											<brp:code>M</brp:code>
										</brp:geslachtsaanduiding>
									</brp:persoon>
									<brp:ouderschap brp:voorkomenSleutel="31">
										<brp:tijdstipRegistratie>1994-03-10T01:00:00.000Z</brp:tijdstipRegistratie>
										<brp:actieInhoud>139</brp:actieInhoud>
										<brp:datumAanvangGeldigheid>1990-06-07</brp:datumAanvangGeldigheid>
										<brp:datumEindeGeldigheid>1991-06-07</brp:datumEindeGeldigheid>
										<brp:actieAanpassingGeldigheid>140</brp:actieAanpassingGeldigheid>
									</brp:ouderschap>
								</brp:ouder>
								<brp:ouder brp:objectSleutel="67" brp:objecttype="Betrokkenheid" brp:voorkomenSleutel="66">
									<brp:tijdstipRegistratie>1994-03-15T01:00:00.000Z</brp:tijdstipRegistratie>
									<brp:actieInhoud>140</brp:actieInhoud>
									<brp:persoon brp:objectSleutel="prZCT6U+/G2skrOO88RPPikqJH7oggYOVZNk2EVXAn4=" brp:objecttype="Persoon">
										<brp:soortCode>P</brp:soortCode>
										<brp:identificatienummers brp:voorkomenSleutel="30">
											<brp:tijdstipRegistratie>1995-10-01T01:00:00.000Z</brp:tijdstipRegistratie>
											<brp:actieInhoud>141</brp:actieInhoud>
											<brp:datumAanvangGeldigheid>1994-03-16</brp:datumAanvangGeldigheid>
											<brp:burgerservicenummer>114946188</brp:burgerservicenummer>
											<brp:administratienummer>1401026062</brp:administratienummer>
										</brp:identificatienummers>
										<brp:samengesteldeNaam brp:voorkomenSleutel="50">
											<brp:tijdstipRegistratie>1995-10-01T01:00:00.000Z</brp:tijdstipRegistratie>
											<brp:actieInhoud>141</brp:actieInhoud>
											<brp:datumAanvangGeldigheid>1994-03-16</brp:datumAanvangGeldigheid>
											<brp:indicatieAfgeleid>N</brp:indicatieAfgeleid>
											<brp:indicatieNamenreeks>N</brp:indicatieNamenreeks>
											<brp:voornamen>Alex</brp:voornamen>
											<brp:voorvoegsel>de</brp:voorvoegsel>
											<brp:scheidingsteken> </brp:scheidingsteken>
											<brp:geslachtsnaamstam>Goede</brp:geslachtsnaamstam>
										</brp:samengesteldeNaam>
										<brp:geboorte brp:voorkomenSleutel="48">
											<brp:tijdstipRegistratie>1995-10-01T01:00:00.000Z</brp:tijdstipRegistratie>
											<brp:actieInhoud>141</brp:actieInhoud>
											<brp:datum>1970-04-12</brp:datum>
											<brp:gemeenteCode>0385</brp:gemeenteCode>
											<brp:landGebiedCode>6030</brp:landGebiedCode>
										</brp:geboorte>
										<brp:geslachtsaanduiding brp:voorkomenSleutel="43">
											<brp:tijdstipRegistratie>1995-10-01T01:00:00.000Z</brp:tijdstipRegistratie>
											<brp:actieInhoud>141</brp:actieInhoud>
											<brp:datumAanvangGeldigheid>1994-03-16</brp:datumAanvangGeldigheid>
											<brp:code>M</brp:code>
										</brp:geslachtsaanduiding>
									</brp:persoon>
									<brp:ouderschap brp:voorkomenSleutel="32">
										<brp:tijdstipRegistratie>1994-03-15T01:00:00.000Z</brp:tijdstipRegistratie>
										<brp:actieInhoud>140</brp:actieInhoud>
										<brp:datumAanvangGeldigheid>1991-06-07</brp:datumAanvangGeldigheid>
									</brp:ouderschap>
									<brp:ouderlijkGezag brp:voorkomenSleutel="2">
										<brp:tijdstipRegistratie>1994-03-10T01:00:00.000Z</brp:tijdstipRegistratie>
										<brp:actieInhoud>135</brp:actieInhoud>
										<brp:datumAanvangGeldigheid>1991-06-07</brp:datumAanvangGeldigheid>
										<brp:datumEindeGeldigheid>1994-03-15</brp:datumEindeGeldigheid>
										<brp:actieAanpassingGeldigheid>134</brp:actieAanpassingGeldigheid>
										<brp:indicatieOuderHeeftGezag>N</brp:indicatieOuderHeeftGezag>
									</brp:ouderlijkGezag>
								</brp:ouder>
							</brp:betrokkenheden>
						</brp:familierechtelijkeBetrekking>
					</brp:kind>
				</brp:betrokkenheden>
				<brp:migratie brp:voorkomenSleutel="10">
					<brp:tijdstipRegistratie>2009-09-06T01:00:00.000Z</brp:tijdstipRegistratie>
					<brp:actieInhoud>130</brp:actieInhoud>
					<brp:datumAanvangGeldigheid>1991-06-07</brp:datumAanvangGeldigheid>
					<brp:soortCode>I</brp:soortCode>
					<brp:landGebiedCode>8031</brp:landGebiedCode>
				</brp:migratie>
				<brp:migratie brp:voorkomenSleutel="9">
					<brp:tijdstipRegistratie>1994-03-10T01:00:00.000Z</brp:tijdstipRegistratie>
					<brp:actieInhoud>129</brp:actieInhoud>
					<brp:tijdstipVerval>1994-03-10T01:00:00.000Z</brp:tijdstipVerval>
					<brp:actieVerval>129</brp:actieVerval>
					<brp:datumAanvangGeldigheid>1991-06-07</brp:datumAanvangGeldigheid>
					<brp:soortCode>I</brp:soortCode>
					<brp:landGebiedCode>8031</brp:landGebiedCode>
				</brp:migratie>
				<brp:reisdocumenten>
					<brp:reisdocument brp:voorkomenSleutel="8" brp:objectSleutel="8" brp:objecttype="PersoonReisdocument">
						<brp:tijdstipRegistratie>2011-01-07T01:00:00.000Z</brp:tijdstipRegistratie>
						<brp:actieInhoud>137</brp:actieInhoud>
						<brp:soortCode>RM</brp:soortCode>
						<brp:nummer>F12345678</brp:nummer>
						<brp:autoriteitVanAfgifte>B0385</brp:autoriteitVanAfgifte>
						<brp:datumIngangDocument>1994-03-16</brp:datumIngangDocument>
						<brp:datumEindeDocument>1995-03-16</brp:datumEindeDocument>
						<brp:datumUitgifte>1994-03-16</brp:datumUitgifte>
						<brp:datumInhoudingVermissing>2011-01-07</brp:datumInhoudingVermissing>
						<brp:aanduidingInhoudingVermissingCode>I</brp:aanduidingInhoudingVermissingCode>
					</brp:reisdocument>
					<brp:reisdocument brp:voorkomenSleutel="7" brp:objectSleutel="7" brp:objecttype="PersoonReisdocument">
						<brp:tijdstipRegistratie>2011-01-17T01:00:00.000Z</brp:tijdstipRegistratie>
						<brp:actieInhoud>136</brp:actieInhoud>
						<brp:soortCode>NI</brp:soortCode>
						<brp:nummer>ID3066675</brp:nummer>
						<brp:autoriteitVanAfgifte>B0385</brp:autoriteitVanAfgifte>
						<brp:datumIngangDocument>2011-01-07</brp:datumIngangDocument>
						<brp:datumEindeDocument>2016-01-07</brp:datumEindeDocument>
						<brp:datumUitgifte>2011-01-07</brp:datumUitgifte>
					</brp:reisdocument>
				</brp:reisdocumenten>
				<brp:persoonskaart brp:voorkomenSleutel="12">
					<brp:tijdstipRegistratie>2011-01-17T01:00:00.000Z</brp:tijdstipRegistratie>
					<brp:actieInhoud>126</brp:actieInhoud>
					<brp:partijCode>038501</brp:partijCode>
					<brp:indicatieVolledigGeconverteerd>J</brp:indicatieVolledigGeconverteerd>
				</brp:persoonskaart>
				<brp:administratieveHandelingen>
					<brp:administratieveHandeling brp:objecttype="AdministratieveHandeling" brp:objectSleutel="12">
						<brp:soortNaam>GBA - Initiele vulling</brp:soortNaam>
						<brp:categorieNaam>GBA - Initiële vulling</brp:categorieNaam>
						<brp:partijCode>199902</brp:partijCode>
						<brp:tijdstipRegistratie>2017-02-07T09:52:24.369Z</brp:tijdstipRegistratie>
						<brp:bronnen>
							<brp:bron brp:objecttype="AdministratieveHandelingBron" brp:objectSleutel="75" brp:communicatieID="document75">
								<brp:document brp:objecttype="Document" brp:objectSleutel="75" brp:voorkomenSleutel="75">
									<brp:soortNaam>Historie conversie</brp:soortNaam>
									<brp:omschrijving>Aanvraagformulier</brp:omschrijving>
									<brp:partijCode>038501</brp:partijCode>
								</brp:document>
							</brp:bron>
							<brp:bron brp:objecttype="AdministratieveHandelingBron" brp:objectSleutel="76" brp:communicatieID="document76">
								<brp:document brp:objecttype="Document" brp:objectSleutel="76" brp:voorkomenSleutel="76">
									<brp:soortNaam>Historie conversie</brp:soortNaam>
									<brp:omschrijving>Kast 1, lade 3</brp:omschrijving>
									<brp:partijCode>038501</brp:partijCode>
								</brp:document>
							</brp:bron>
							<brp:bron brp:objecttype="AdministratieveHandelingBron" brp:objectSleutel="72" brp:communicatieID="document72">
								<brp:document brp:objecttype="Document" brp:objectSleutel="72" brp:voorkomenSleutel="72">
									<brp:soortNaam>Historie conversie</brp:soortNaam>
									<brp:omschrijving>PL gerelateerde</brp:omschrijving>
									<brp:partijCode>038501</brp:partijCode>
								</brp:document>
							</brp:bron>
							<brp:bron brp:objecttype="AdministratieveHandelingBron" brp:objectSleutel="73" brp:communicatieID="document73">
								<brp:document brp:objecttype="Document" brp:objectSleutel="73" brp:voorkomenSleutel="73">
									<brp:soortNaam>Historie conversie</brp:soortNaam>
									<brp:aktenummer>1 Q0029</brp:aktenummer>
									<brp:partijCode>038501</brp:partijCode>
								</brp:document>
							</brp:bron>
							<brp:bron brp:objecttype="AdministratieveHandelingBron" brp:objectSleutel="80" brp:communicatieID="document80">
								<brp:document brp:objecttype="Document" brp:objectSleutel="80" brp:voorkomenSleutel="80">
									<brp:soortNaam>Historie conversie</brp:soortNaam>
									<brp:omschrijving>PL gerelateerde</brp:omschrijving>
									<brp:partijCode>038501</brp:partijCode>
								</brp:document>
							</brp:bron>
							<brp:bron brp:objecttype="AdministratieveHandelingBron" brp:objectSleutel="77" brp:communicatieID="document77">
								<brp:document brp:objecttype="Document" brp:objectSleutel="77" brp:voorkomenSleutel="77">
									<brp:soortNaam>Historie conversie</brp:soortNaam>
									<brp:aktenummer>1 Q0029</brp:aktenummer>
									<brp:partijCode>038501</brp:partijCode>
								</brp:document>
							</brp:bron>
							<brp:bron brp:objecttype="AdministratieveHandelingBron" brp:objectSleutel="79" brp:communicatieID="document79">
								<brp:document brp:objecttype="Document" brp:objectSleutel="79" brp:voorkomenSleutel="79">
									<brp:soortNaam>Historie conversie</brp:soortNaam>
									<brp:aktenummer>1 Q0029</brp:aktenummer>
									<brp:partijCode>038501</brp:partijCode>
								</brp:document>
							</brp:bron>
							<brp:bron brp:objecttype="AdministratieveHandelingBron" brp:objectSleutel="74" brp:communicatieID="document74">
								<brp:document brp:objecttype="Document" brp:objectSleutel="74" brp:voorkomenSleutel="74">
									<brp:soortNaam>Historie conversie</brp:soortNaam>
									<brp:omschrijving>PKA</brp:omschrijving>
									<brp:partijCode>038501</brp:partijCode>
								</brp:document>
							</brp:bron>
							<brp:bron brp:objecttype="AdministratieveHandelingBron" brp:objectSleutel="78" brp:communicatieID="document78">
								<brp:document brp:objecttype="Document" brp:objectSleutel="78" brp:voorkomenSleutel="78">
									<brp:soortNaam>Historie conversie</brp:soortNaam>
									<brp:omschrijving>PK</brp:omschrijving>
									<brp:partijCode>038501</brp:partijCode>
								</brp:document>
							</brp:bron>
						</brp:bronnen>
						<brp:bijgehoudenActies>
							<brp:actie brp:objecttype="Actie" brp:objectSleutel="133">
								<brp:soortNaam>Conversie GBA</brp:soortNaam>
								<brp:partijCode>199902</brp:partijCode>
							</brp:actie>
							<brp:actie brp:objecttype="Actie" brp:objectSleutel="126">
								<brp:soortNaam>Conversie GBA</brp:soortNaam>
								<brp:partijCode>199902</brp:partijCode>
							</brp:actie>
							<brp:actie brp:objecttype="Actie" brp:objectSleutel="136">
								<brp:soortNaam>Conversie GBA</brp:soortNaam>
								<brp:partijCode>199902</brp:partijCode>
								<brp:datumOntlening>2011-01-17</brp:datumOntlening>
								<brp:bronnen>
									<brp:bron brp:objecttype="ActieBron" brp:objectSleutel="75" brp:referentieID="document75"/>
								</brp:bronnen>
							</brp:actie>
							<brp:actie brp:objecttype="Actie" brp:objectSleutel="137">
								<brp:soortNaam>Conversie GBA</brp:soortNaam>
								<brp:partijCode>199902</brp:partijCode>
								<brp:datumOntlening>1994-03-16</brp:datumOntlening>
								<brp:bronnen>
									<brp:bron brp:objecttype="ActieBron" brp:objectSleutel="76" brp:referentieID="document76"/>
								</brp:bronnen>
							</brp:actie>
							<brp:actie brp:objecttype="Actie" brp:objectSleutel="130">
								<brp:soortNaam>Conversie GBA</brp:soortNaam>
								<brp:partijCode>199902</brp:partijCode>
							</brp:actie>
							<brp:actie brp:objecttype="Actie" brp:objectSleutel="125">
								<brp:soortNaam>Conversie GBA</brp:soortNaam>
								<brp:partijCode>199902</brp:partijCode>
								<brp:datumOntlening>1994-03-16</brp:datumOntlening>
								<brp:bronnen>
									<brp:bron brp:objecttype="ActieBron" brp:objectSleutel="72" brp:referentieID="document72"/>
								</brp:bronnen>
							</brp:actie>
							<brp:actie brp:objecttype="Actie" brp:objectSleutel="127">
								<brp:soortNaam>Conversie GBA</brp:soortNaam>
								<brp:partijCode>199902</brp:partijCode>
								<brp:bronnen>
									<brp:bron brp:objecttype="ActieBron" brp:objectSleutel="73" brp:referentieID="document73"/>
								</brp:bronnen>
							</brp:actie>
							<brp:actie brp:objecttype="Actie" brp:objectSleutel="141">
								<brp:soortNaam>Conversie GBA</brp:soortNaam>
								<brp:partijCode>199902</brp:partijCode>
								<brp:datumOntlening>1994-03-16</brp:datumOntlening>
								<brp:bronnen>
									<brp:bron brp:objecttype="ActieBron" brp:objectSleutel="80" brp:referentieID="document80"/>
								</brp:bronnen>
							</brp:actie>
							<brp:actie brp:objecttype="Actie" brp:objectSleutel="131">
								<brp:soortNaam>Conversie GBA</brp:soortNaam>
								<brp:partijCode>199902</brp:partijCode>
							</brp:actie>
							<brp:actie brp:objecttype="Actie" brp:objectSleutel="134">
								<brp:soortNaam>Conversie GBA</brp:soortNaam>
								<brp:partijCode>199902</brp:partijCode>
							</brp:actie>
							<brp:actie brp:objecttype="Actie" brp:objectSleutel="138">
								<brp:soortNaam>Conversie GBA</brp:soortNaam>
								<brp:partijCode>199902</brp:partijCode>
								<brp:bronnen>
									<brp:bron brp:objecttype="ActieBron" brp:objectSleutel="77" brp:referentieID="document77"/>
								</brp:bronnen>
							</brp:actie>
							<brp:actie brp:objecttype="Actie" brp:objectSleutel="140">
								<brp:soortNaam>Conversie GBA</brp:soortNaam>
								<brp:partijCode>199902</brp:partijCode>
								<brp:bronnen>
									<brp:bron brp:objecttype="ActieBron" brp:objectSleutel="79" brp:referentieID="document79"/>
								</brp:bronnen>
							</brp:actie>
							<brp:actie brp:objecttype="Actie" brp:objectSleutel="128">
								<brp:soortNaam>Conversie GBA</brp:soortNaam>
								<brp:partijCode>199902</brp:partijCode>
								<brp:datumOntlening>1994-03-10</brp:datumOntlening>
								<brp:bronnen>
									<brp:bron brp:objecttype="ActieBron" brp:objectSleutel="74" brp:referentieID="document74"/>
								</brp:bronnen>
							</brp:actie>
							<brp:actie brp:objecttype="Actie" brp:objectSleutel="129">
								<brp:soortNaam>Conversie GBA</brp:soortNaam>
								<brp:partijCode>199902</brp:partijCode>
							</brp:actie>
							<brp:actie brp:objecttype="Actie" brp:objectSleutel="132">
								<brp:soortNaam>Conversie GBA</brp:soortNaam>
								<brp:partijCode>199902</brp:partijCode>
							</brp:actie>
							<brp:actie brp:objecttype="Actie" brp:objectSleutel="135">
								<brp:soortNaam>Conversie GBA</brp:soortNaam>
								<brp:partijCode>199902</brp:partijCode>
							</brp:actie>
							<brp:actie brp:objecttype="Actie" brp:objectSleutel="139">
								<brp:soortNaam>Conversie GBA</brp:soortNaam>
								<brp:partijCode>199902</brp:partijCode>
								<brp:datumOntlening>1994-03-10</brp:datumOntlening>
								<brp:bronnen>
									<brp:bron brp:objecttype="ActieBron" brp:objectSleutel="78" brp:referentieID="document78"/>
								</brp:bronnen>
							</brp:actie>
						</brp:bijgehoudenActies>
					</brp:administratieveHandeling>
				</brp:administratieveHandelingen>
			</brp:persoon>
		</brp:geselecteerdePersoon>
		<brp:geselecteerdePersoon>
			<brp:meldingen>
				<brp:melding brp:objecttype="Melding" brp:referentieID="2">
					<brp:regelCode>R1343</brp:regelCode>
					<brp:soortNaam>Waarschuwing</brp:soortNaam>
					<brp:melding>Bij deze persoon is een verstrekkingsbeperking vastgelegd.</brp:melding>
				</brp:melding>
			</brp:meldingen>
			<brp:persoon brp:objectSleutel="prZCT6U+/G2skrOO88RPPikqJH7oggYOVZNk2EVXAn4=" brp:objecttype="Persoon" brp:communicatieID="2">
				<brp:soortCode>I</brp:soortCode>
				<brp:identificatienummers brp:voorkomenSleutel="30">
					<brp:tijdstipRegistratie>1995-10-01T01:00:00.000Z</brp:tijdstipRegistratie>
					<brp:actieInhoud>141</brp:actieInhoud>
					<brp:datumAanvangGeldigheid>1994-03-16</brp:datumAanvangGeldigheid>
					<brp:burgerservicenummer>114946188</brp:burgerservicenummer>
					<brp:administratienummer>1401026062</brp:administratienummer>
				</brp:identificatienummers>
				<brp:samengesteldeNaam brp:voorkomenSleutel="50">
					<brp:tijdstipRegistratie>1995-10-01T01:00:00.000Z</brp:tijdstipRegistratie>
					<brp:actieInhoud>141</brp:actieInhoud>
					<brp:datumAanvangGeldigheid>1994-03-16</brp:datumAanvangGeldigheid>
					<brp:indicatieAfgeleid>N</brp:indicatieAfgeleid>
					<brp:indicatieNamenreeks>N</brp:indicatieNamenreeks>
					<brp:voornamen>Alex</brp:voornamen>
					<brp:voorvoegsel>de</brp:voorvoegsel>
					<brp:scheidingsteken> </brp:scheidingsteken>
					<brp:geslachtsnaamstam>Goede</brp:geslachtsnaamstam>
				</brp:samengesteldeNaam>
				<brp:geboorte brp:voorkomenSleutel="48">
					<brp:tijdstipRegistratie>1995-10-01T01:00:00.000Z</brp:tijdstipRegistratie>
					<brp:actieInhoud>141</brp:actieInhoud>
					<brp:datum>1970-04-12</brp:datum>
					<brp:gemeenteCode>0385</brp:gemeenteCode>
					<brp:landGebiedCode>6030</brp:landGebiedCode>
				</brp:geboorte>
				<brp:geslachtsaanduiding brp:voorkomenSleutel="43">
					<brp:tijdstipRegistratie>1995-10-01T01:00:00.000Z</brp:tijdstipRegistratie>
					<brp:actieInhoud>141</brp:actieInhoud>
					<brp:datumAanvangGeldigheid>1994-03-16</brp:datumAanvangGeldigheid>
					<brp:code>M</brp:code>
				</brp:geslachtsaanduiding>
				<!-- etc etc etc -->
			</brp:persoon>
		</brp:geselecteerdePersoon>
		<brp:geselecteerdePersoon>
			<brp:persoon brp:objectSleutel="prZCT6U+/G3J7ik/h1Pu5ykqJH7oggYOVZNk2EVXAn4=" brp:objecttype="Persoon">
				<brp:soortCode>P</brp:soortCode>
				<brp:identificatienummers brp:voorkomenSleutel="29">
					<brp:tijdstipRegistratie>1995-10-01T01:00:00.000Z</brp:tijdstipRegistratie>
					<brp:actieInhoud>125</brp:actieInhoud>
					<brp:datumAanvangGeldigheid>1994-03-16</brp:datumAanvangGeldigheid>
					<brp:burgerservicenummer>116108873</brp:burgerservicenummer>
					<brp:administratienummer>1401025983</brp:administratienummer>
				</brp:identificatienummers>
				<brp:samengesteldeNaam brp:voorkomenSleutel="48">
					<brp:tijdstipRegistratie>1995-10-01T01:00:00.000Z</brp:tijdstipRegistratie>
					<brp:actieInhoud>125</brp:actieInhoud>
					<brp:datumAanvangGeldigheid>1994-03-16</brp:datumAanvangGeldigheid>
					<brp:indicatieAfgeleid>N</brp:indicatieAfgeleid>
					<brp:indicatieNamenreeks>N</brp:indicatieNamenreeks>
					<brp:voornamen>José</brp:voornamen>
					<brp:voorvoegsel>van 't</brp:voorvoegsel>
					<brp:scheidingsteken> </brp:scheidingsteken>
					<brp:geslachtsnaamstam>Wiel</brp:geslachtsnaamstam>
				</brp:samengesteldeNaam>
				<brp:geboorte brp:voorkomenSleutel="46">
					<brp:tijdstipRegistratie>1995-10-01T01:00:00.000Z</brp:tijdstipRegistratie>
					<brp:actieInhoud>125</brp:actieInhoud>
					<brp:datum>1971-01-07</brp:datum>
					<brp:gemeenteCode>0344</brp:gemeenteCode>
					<brp:landGebiedCode>6030</brp:landGebiedCode>
				</brp:geboorte>
				<brp:geslachtsaanduiding brp:voorkomenSleutel="41">
					<brp:tijdstipRegistratie>1995-10-01T01:00:00.000Z</brp:tijdstipRegistratie>
					<brp:actieInhoud>125</brp:actieInhoud>
					<brp:datumAanvangGeldigheid>1994-03-16</brp:datumAanvangGeldigheid>
					<brp:code>V</brp:code>
				</brp:geslachtsaanduiding>
				<!-- etc etc etc -->
			</brp:persoon>
		</brp:geselecteerdePersoon>
	</brp:geselecteerdePersonen>
</brp:lvg_selVerwerkSelectieresultaatSet>
