<?xml version="1.0" encoding="UTF-8" standalone="no"?>
<!DOCTYPE tiles-definitions PUBLIC "-//Apache Software Foundation//DTD Tiles Configuration 2.1//EN" "http://tiles.apache.org/dtds/tiles-config_2_1.dtd">
<tiles-definitions>
    <definition extends="default" name="hispersindicaties/list">
        <put-attribute name="body" value="/WEB-INF/views/hispersindicaties/list.jspx"/>
    </definition>
<definition extends="default" name="hispersindicaties/show">
        <put-attribute name="body" value="/WEB-INF/views/hispersindicaties/show.jspx"/>
    </definition>
<definition extends="default" name="hispersindicaties/create">
        <put-attribute name="body" value="/WEB-INF/views/hispersindicaties/create.jspx"/>
    </definition>
<definition extends="default" name="hispersindicaties/update">
        <put-attribute name="body" value="/WEB-INF/views/hispersindicaties/update.jspx"/>
    </definition>
</tiles-definitions>
